[
    {"num": 1, "id": 3701, "traditional": "親", "simplified": "亲", "pinyin": "qīn", "zhuyin": "ㄑㄧㄣ", "type": "Vs", "tags": ["cercano", "íntimo", "relación", "familia", "adjetivo", "close", "intimate", "relationship", "family", "adjective", "proche", "intime", "relation", "famille", "adjectif", "nah", "eng", "Beziehung", "Familie", "Adjektiv", "vicino", "intimo", "relazione", "famiglia", "aggettivo", "próximo", "íntimo", "relacionamento", "família", "adjetivo"], "translation": {"es": "cercano (en una relación familiar)", "en": "close (as of familial relationship)", "fr": "proche (relation familiale)", "de": "eng (in familiärer Beziehung)", "it": "stretto (in un rapporto familiare)", "pt": "próximo (em um relacionamento familiar)"}},
    {"num": 2, "id": 3702, "traditional": "爺爺", "simplified": "爷爷", "pinyin": "yéye", "zhuyin": "ㄧㄝˊ ㄧㄝ·", "type": "N", "tags": ["abuelo", "familia", "paterno", "pariente", "hombre", "grandfather", "family", "paternal", "relative", "man", "grand-père", "famille", "paternel", "parent", "homme", "Großvater", "Familie", "väterlicherseits", "Verwandter", "Mann", "nonno", "famiglia", "paterno", "parente", "uomo", "avô", "família", "paterno", "parente", "homem"], "translation": {"es": "abuelo (paterno)", "en": "grandpa (father's side)", "fr": "grand-père (côté paternel)", "de": "Opa (väterlicherseits)", "it": "nonno (paterno)", "pt": "avô (paterno)"}},
    {"num": 3, "id": 3703, "traditional": "鄰居", "simplified": "邻居", "pinyin": "línjū", "zhuyin": "ㄌㄧㄣˊ ㄐㄩ", "type": "N", "tags": ["vecino", "comunidad", "persona", "cerca", "residente", "neighbor", "community", "person", "nearby", "resident", "voisin", "communauté", "personne", "proche", "résident", "Nachbar", "Gemeinschaft", "Person", "nahe", "Anwohner", "vicino", "comunità", "persona", "vicino", "residente", "vizinho", "comunidade", "pessoa", "perto", "residente"], "translation": {"es": "vecino", "en": "neighbor", "fr": "voisin", "de": "Nachbar", "it": "vicino di casa", "pt": "vizinho"}},
    {"num": 4, "id": 3704, "traditional": "狗", "simplified": "狗", "pinyin": "gǒu", "zhuyin": "ㄍㄡˇ", "type": "N", "tags": ["perro", "animal", "mascota", "mamífero", "doméstico", "dog", "animal", "pet", "mammal", "domestic", "chien", "animal", "animal de compagnie", "mammifère", "domestique", "Hund", "Tier", "Haustier", "Säugetier", "domestiziert", "cane", "animale", "animale domestico", "mammifero", "domestico", "cão", "cachorro", "animal", "animal de estimação", "mamífero", "doméstico"], "translation": {"es": "perro", "en": "dog", "fr": "chien", "de": "Hund", "it": "cane", "pt": "cachorro"}},
    {"num": 5, "id": 3705, "traditional": "叫", "simplified": "叫", "pinyin": "jiào", "zhuyin": "ㄐㄧㄠˋ", "type": "Vi", "tags": ["acción", "ladrar", "gritar", "sonido", "animal", "action", "to bark", "to shout", "sound", "animal", "action", "aboyer", "crier", "son", "animal", "Aktion", "bellen", "schreien", "Geräusch", "Tier", "azione", "abbaiare", "gridare", "suono", "animale", "ação", "latir", "gritar", "som", "animal"], "translation": {"es": "ladrar", "en": "to bark", "fr": "aboyer", "de": "bellen", "it": "abbaiare", "pt": "latir"}},
    {"num": 6, "id": 3706, "traditional": "嗯", "simplified": "嗯", "pinyin": "en", "zhuyin": "ㄣ", "type": "Ptc", "tags": ["interjección", "acuerdo", "sí", "afirmación", "sonido", "interjection", "agreement", "yes", "affirmation", "sound", "interjection", "accord", "oui", "affirmation", "son", "Interjektion", "Zustimmung", "ja", "Bestätigung", "Laut", "interiezione", "accordo", "sì", "affermazione", "suono", "interjeição", "acordo", "sim", "afirmação", "som"], "translation": {"es": "ajá, sí", "en": "an interjection indicating the speaker's agreement", "fr": "hum", "de": "hm", "it": "ehm", "pt": "uhum"}},
    {"num": 7, "id": 3707, "traditional": "奶奶", "simplified": "奶奶", "pinyin": "nǎinai", "zhuyin": "ㄋㄞˇ ㄋㄞˇ", "type": "N", "tags": ["abuela", "familia", "paterno", "pariente", "mujer", "grandmother", "family", "paternal", "relative", "woman", "grand-mère", "famille", "paternel", "parent", "femme", "Großmutter", "Familie", "väterlicherseits", "Verwandte", "Frau", "nonna", "famiglia", "paterno", "parente", "donna", "avó", "família", "paterna", "parente", "mulher"], "translation": {"es": "abuela (paterna)", "en": "grandma (father's side)", "fr": "grand-mère (côté paternel)", "de": "Oma (väterlicherseits)", "it": "nonna (paterna)", "pt": "avó (paterna)"}},
    {"num": 8, "id": 3708, "traditional": "過世", "simplified": "过世", "pinyin": "guòshì", "zhuyin": "ㄍㄨㄛˋ ㄕˋ", "type": "Vp", "tags": ["morir", "fallecer", "muerte", "respetuoso", "verbo", "to pass away", "to die", "death", "honorific", "verb", "décéder", "mourir", "mort", "honorifique", "verbe", "versterben", "sterben", "Tod", "ehrenvoll", "Verb", "passare a miglior vita", "morire", "morte", "onorifico", "verbo", "falecer", "morrer", "morte", "honorífico", "verbo"], "translation": {"es": "fallecer", "en": "to die, pass away (honorific)", "fr": "décéder", "de": "versterben", "it": "passare a miglior vita", "pt": "falecer"}},
    {"num": 9, "id": 3709, "traditional": "領養", "simplified": "领养", "pinyin": "lǐngyǎng", "zhuyin": "ㄌㄧㄥˇ ㄧㄤˇ", "type": "V", "tags": ["acción", "adoptar", "familia", "niño", "mascota", "action", "to adopt", "family", "child", "pet", "action", "adopter", "famille", "enfant", "animal de compagnie", "Aktion", "adoptieren", "Familie", "Kind", "Haustier", "azione", "adottare", "famiglia", "bambino", "animale domestico", "ação", "adotar", "família", "criança", "animal de estimação"], "translation": {"es": "adoptar", "en": "to adopt", "fr": "adopter", "de": "adoptieren", "it": "adottare", "pt": "adotar"}},
    {"num": 10, "id": 3710, "traditional": "隻", "simplified": "只", "pinyin": "zhī", "zhuyin": "ㄓ", "type": "M", "tags": ["clasificador", "animales", "gramática", "uno de un par", "cantidad", "measure word", "animals", "grammar", "one of a pair", "quantity", "classificateur", "animaux", "grammaire", "un d'une paire", "quantité", "Zähleinheitswort", "Tiere", "Grammatik", "einer von einem Paar", "Menge", "classificatore", "animali", "grammatica", "uno di una coppia", "quantità", "classificador", "animais", "gramática", "um de um par", "quantidade"], "translation": {"es": "clasificador para animales", "en": "measure word for animals", "fr": "classificateur pour les animaux", "de": "Zähleinheitswort für Tiere", "it": "classificatore per animali", "pt": "classificador para animais"}},
    {"num": 11, "id": 3711, "traditional": "可愛", "simplified": "可爱", "pinyin": "kě'ài", "zhuyin": "ㄎㄜˇ ㄞˋ", "type": "Vs", "tags": ["adorable", "lindo", "mono", "apariencia", "adjetivo", "cute", "lovely", "adorable", "appearance", "adjective", "mignon", "adorable", "apparence", "adjectif", "süß", "niedlich", "Aussehen", "Adjektiv", "carino", "adorabile", "aspetto", "aggettivo", "fofo", "adorável", "aparência", "adjetivo"], "translation": {"es": "adorable, lindo", "en": "cute", "fr": "mignon", "de": "süß, niedlich", "it": "carino", "pt": "fofo"}},
    {"num": 12, "id": 3712, "traditional": "孤單", "simplified": "孤单", "pinyin": "gūdān", "zhuyin": "ㄍㄨ ㄉㄢ", "type": "Vs", "tags": ["solitario", "sentimiento", "solo", "emoción", "adjetivo", "lonely", "feeling", "alone", "emotion", "adjective", "solitaire", "sentiment", "seul", "émotion", "adjectif", "einsam", "Gefühl", "allein", "Emotion", "Adjektiv", "solitario", "sentimento", "solo", "emozione", "aggettivo", "solitário", "sentimento", "sozinho", "emoção", "adjetivo"], "translation": {"es": "solitario", "en": "lonely", "fr": "solitaire", "de": "einsam", "it": "solitario", "pt": "solitário"}},
    {"num": 13, "id": 3713, "traditional": "牠", "simplified": "它", "pinyin": "tā", "zhuyin": "ㄊㄚ", "type": "N", "tags": ["pronombre", "ello", "animal", "objeto", "neutro", "pronoun", "it", "animal", "object", "neuter", "pronom", "il/elle (animal)", "objet", "neutre", "Pronomen", "es (Tier)", "Objekt", "sächlich", "pronome", "esso/essa (animale)", "oggetto", "neutro", "pronome", "ele/ela (animal)", "objeto", "neutro"], "translation": {"es": "ello (para animales)", "en": "it (animals)", "fr": "il, elle (animal)", "de": "es (Tier)", "it": "esso, essa (animale)", "pt": "ele, ela (animal)"}},
    {"num": 14, "id": 3714, "traditional": "髒", "simplified": "脏", "pinyin": "zāng", "zhuyin": "ㄗㄤ", "type": "Vs", "tags": ["sucio", "adjetivo", "limpieza", "negativo", "higiene", "dirty", "adjective", "cleanliness", "negative", "hygiene", "sale", "adjectif", "propreté", "négatif", "hygiène", "schmutzig", "Adjektiv", "Sauberkeit", "negativ", "Hygiene", "sporco", "aggettivo", "pulizia", "negativo", "igiene", "sujo", "adjetivo", "limpeza", "negativo", "higiene"], "translation": {"es": "sucio", "en": "dirty", "fr": "sale", "de": "schmutzig", "it": "sporco", "pt": "sujo"}},
    {"num": 15, "id": 3715, "traditional": "洗澡", "simplified": "洗澡", "pinyin": "xǐzǎo", "zhuyin": "ㄒㄧˇ ㄗㄠˇ", "type": "V-sep", "tags": ["acción", "bañarse", "ducharse", "higiene", "cuerpo", "action", "to take a bath", "to take a shower", "hygiene", "body", "action", "prendre un bain", "se doucher", "hygiène", "corps", "Aktion", "baden", "duschen", "Hygiene", "Körper", "azione", "fare il bagno", "fare la doccia", "igiene", "corpo", "ação", "tomar banho", "higiene", "corpo"], "translation": {"es": "bañarse", "en": "to take a bath", "fr": "prendre un bain", "de": "baden", "it": "fare il bagno", "pt": "tomar banho"}},
    {"num": 16, "id": 3716, "traditional": "養", "simplified": "养", "pinyin": "yǎng", "zhuyin": "ㄧㄤˇ", "type": "V", "tags": ["acción", "criar", "mantener", "cuidar", "mascota", "action", "to raise", "to keep", "to care for", "pet", "action", "élever", "garder", "s'occuper de", "animal de compagnie", "Aktion", "aufziehen", "halten", "pflegen", "Haustier", "azione", "allevare", "tenere", "prendersi cura di", "animale domestico", "ação", "criar", "manter", "cuidar de", "animal de estimação"], "translation": {"es": "criar, mantener (una mascota)", "en": "to raise, to keep", "fr": "élever, garder", "de": "aufziehen, halten", "it": "allevare, tenere", "pt": "criar, manter"}},
    {"num": 17, "id": 3717, "traditional": "亂", "simplified": "乱", "pinyin": "luàn", "zhuyin": "ㄌㄨㄢˋ", "type": "Adv", "tags": ["adverbio", "arbitrariamente", "desordenado", "al azar", "sin razón", "adverb", "arbitrarily", "messy", "randomly", "without reason", "adverbe", "arbitrairement", "en désordre", "au hasard", "sans raison", "Adverb", "willkürlich", "unordentlich", "zufällig", "ohne Grund", "avverbio", "arbitrariamente", "disordinato", "casualmente", "senza ragione", "advérbio", "arbitrariamente", "bagunçado", "aleatoriamente", "sem motivo"], "translation": {"es": "arbitrariamente, sin ton ni son", "en": "arbitrarily, without rhyme or reason", "fr": "arbitrairement", "de": "willkürlich", "it": "arbitrariamente", "pt": "arbitrariamente"}},
    {"num": 18, "id": 3718, "traditional": "咬", "simplified": "咬", "pinyin": "yǎo", "zhuyin": "ㄧㄠˇ", "type": "V", "tags": ["acción", "morder", "dientes", "animal", "dolor", "action", "to bite", "teeth", "animal", "pain", "action", "mordre", "dents", "animal", "douleur", "Aktion", "beißen", "Zähne", "Tier", "Schmerz", "azione", "mordere", "denti", "animale", "dolore", "ação", "morder", "dentes", "animal", "dor"], "translation": {"es": "morder", "en": "to bite", "fr": "mordre", "de": "beißen", "it": "mordere", "pt": "morder"}},
    {"num": 19, "id": 3719, "traditional": "打", "simplified": "打", "pinyin": "dǎ", "zhuyin": "ㄉㄚˇ", "type": "V", "tags": ["acción", "golpear", "pegar", "pelear", "violencia", "action", "to hit", "to beat", "to smack", "to slap", "fight", "action", "frapper", "battre", "gifler", "combat", "Aktion", "schlagen", "hauen", "kämpfen", "Gewalt", "azione", "colpire", "picchiare", "schiaffeggiare", "combattere", "ação", "bater", "golpear", "lutar", "violência"], "translation": {"es": "golpear, pegar", "en": "to hit, beat, smack, slap", "fr": "frapper", "de": "schlagen", "it": "colpire, picchiare", "pt": "bater, golpear"}},
    {"num": 20, "id": 3720, "traditional": "分手", "simplified": "分手", "pinyin": "fēnshǒu", "zhuyin": "ㄈㄣ ㄕㄡˇ", "type": "Vp", "tags": ["acción", "romper", "separarse", "relación", "romántico", "action", "to break up", "to separate", "relationship", "romantic", "action", "rompre", "se séparer", "relation", "romantique", "Aktion", "sich trennen", "Beziehung", "romantisch", "azione", "rompere", "separarsi", "relazione", "romantico", "ação", "terminar", "separar-se", "relacionamento", "romântico"], "translation": {"es": "romper (una relación)", "en": "to break up (said of romantic relationships)", "fr": "rompre (une relation amoureuse)", "de": "sich trennen (Beziehung)", "it": "lasciarsi (relazione sentimentale)", "pt": "terminar (um relacionamento)"}},
    {"num": 21, "id": 3721, "traditional": "緊張", "simplified": "紧张", "pinyin": "jǐnzhāng", "zhuyin": "ㄐㄧㄣˇ ㄓㄤ", "type": "Vs", "tags": ["tenso", "nervioso", "sentimiento", "estrés", "emoción", "tense", "nervous", "feeling", "stress", "emotion", "tendu", "nerveux", "sentiment", "stress", "émotion", "angespannt", "nervös", "Gefühl", "Stress", "Emotion", "teso", "nervoso", "sentimento", "stress", "emozione", "tenso", "nervoso", "sentimento", "estresse", "emoção"], "translation": {"es": "tenso, nervioso", "en": "tense", "fr": "tendu, nerveux", "de": "angespannt, nervös", "it": "teso", "pt": "tenso"}},
    {"num": 22, "id": 3722, "traditional": "減輕", "simplified": "减轻", "pinyin": "jiǎnqīng", "zhuyin": "ㄐㄧㄢˇ ㄑㄧㄥ", "type": "V", "tags": ["acción", "reducir", "aliviar", "disminuir", "peso", "action", "to reduce", "to ease", "to lighten", "weight", "action", "réduire", "alléger", "soulager", "poids", "Aktion", "reduzieren", "erleichtern", "verringern", "Gewicht", "azione", "ridurre", "alleviare", "alleggerire", "peso", "ação", "reduzir", "aliviar", "diminuir", "peso"], "translation": {"es": "reducir, aligerar", "en": "to reduce", "fr": "réduire", "de": "reduzieren", "it": "ridurre", "pt": "reduzir"}},
    {"num": 23, "id": 3723, "traditional": "送", "simplified": "送", "pinyin": "sòng", "zhuyin": "ㄙㄨㄥˋ", "type": "V", "tags": ["acción", "llevar", "acompañar", "entregar", "regalar", "action", "to take to", "to see off", "to deliver", "to give as a gift", "action", "emmener", "raccompagner", "livrer", "offrir", "Aktion", "bringen", "begleiten", "liefern", "schenken", "azione", "portare a", "accompagnare", "consegnare", "regalare", "ação", "levar a", "acompanhar", "entregar", "presentear"], "translation": {"es": "llevar a", "en": "to take to", "fr": "emmener à", "de": "bringen zu", "it": "portare a", "pt": "levar para"}},
    {"num": 24, "id": 3724, "traditional": "美容院", "simplified": "美容院", "pinyin": "měiróngyuàn", "zhuyin": "ㄇㄟˇ ㄖㄨㄥˊ ㄩㄢˋ", "type": "N", "tags": ["salón de belleza", "estética", "cuidado personal", "lugar", "belleza", "beauty salon", "aesthetics", "personal care", "place", "beauty", "salon de beauté", "esthétique", "soins personnels", "lieu", "beauté", "Schönheitssalon", "Ästhetik", "Körperpflege", "Ort", "Schönheit", "salone di bellezza", "estetica", "cura personale", "luogo", "bellezza", "salão de beleza", "estética", "cuidados pessoais", "lugar", "beleza"], "translation": {"es": "salón de belleza", "en": "beauty salon", "fr": "salon de beauté", "de": "Schönheitssalon", "it": "salone di bellezza", "pt": "salão de beleza"}},
    {"num": 25, "id": 3725, "traditional": "推車", "simplified": "推车", "pinyin": "tuīchē", "zhuyin": "ㄊㄨㄟ ㄔㄜ", "type": "N", "tags": ["cochecito", "carrito", "bebé", "niño", "objeto", "stroller", "cart", "baby", "child", "object", "poussette", "chariot", "bébé", "enfant", "objet", "Kinderwagen", "Wagen", "Baby", "Kind", "Objekt", "passeggino", "carrello", "bambino", "neonato", "oggetto", "carrinho de bebê", "carrinho", "bebê", "criança", "objeto"], "translation": {"es": "cochecito de bebé", "en": "stroller", "fr": "poussette", "de": "Kinderwagen", "it": "passeggino", "pt": "carrinho de bebê"}},
    {"num": 26, "id": 3726, "traditional": "主人", "simplified": "主人", "pinyin": "zhǔrén", "zhuyin": "ㄓㄨˇ ㄖㄣˊ", "type": "N", "tags": ["dueño", "amo", "propietario", "mascota", "persona", "master", "owner", "proprietor", "pet", "person", "maître", "propriétaire", "animal de compagnie", "personne", "Besitzer", "Herr", "Eigentümer", "Haustier", "Person", "padrone", "proprietario", "animale domestico", "persona", "dono", "proprietário", "animal de estimação", "pessoa"], "translation": {"es": "dueño, amo", "en": "master, owner", "fr": "maître, propriétaire", "de": "Besitzer, Herr", "it": "padrone, proprietario", "pt": "dono"}},
    {"num": 27, "id": 3727, "traditional": "相處", "simplified": "相处", "pinyin": "xiāngchǔ", "zhuyin": "ㄒㄧㄤ ㄔㄨˇ", "type": "Vi", "tags": ["llevarse bien", "pasar tiempo juntos", "relación", "social", "interacción", "to get along (with)", "to spend time together", "relationship", "social", "interaction", "s'entendre avec", "passer du temps ensemble", "relation", "social", "interaction", "sich verstehen mit", "Zeit zusammen verbringen", "Beziehung", "sozial", "Interaktion", "andare d'accordo con", "passare del tempo insieme", "relazione", "sociale", "interazione", "dar-se bem com", "passar tempo juntos", "relacionamento", "social", "interação"], "translation": {"es": "llevarse bien, pasar tiempo juntos", "en": "to get along (with), to spend time together", "fr": "s'entendre avec, passer du temps ensemble", "de": "sich verstehen mit, Zeit zusammen verbringen", "it": "andare d'accordo, passare del tempo insieme", "pt": "dar-se bem, passar tempo juntos"}},
    {"num": 28, "id": 3728, "traditional": "生", "simplified": "生", "pinyin": "shēng", "zhuyin": "ㄕㄥ", "type": "V", "tags": ["acción", "dar a luz", "nacer", "vida", "biología", "action", "to give birth", "to be born", "life", "biology", "action", "donner naissance", "naître", "vie", "biologie", "Aktion", "gebären", "geboren werden", "Leben", "Biologie", "azione", "partorire", "nascere", "vita", "biologia", "ação", "dar à luz", "nascer", "vida", "biologia"], "translation": {"es": "dar a luz", "en": "to give birth, to bear", "fr": "donner naissance", "de": "gebären", "it": "partorire", "pt": "dar à luz"}},
    {"num": 29, "id": 3729, "traditional": "寵物", "simplified": "宠物", "pinyin": "chǒngwù", "zhuyin": "ㄔㄨㄥˇ ㄨˋ", "type": "N", "tags": ["mascota", "animal", "doméstico", "compañero", "familia", "pet", "animal", "domestic", "companion", "family", "animal de compagnie", "animal", "domestique", "compagnon", "famille", "Haustier", "Tier", "domestiziert", "Begleiter", "Familie", "animale domestico", "animale", "compagno", "famiglia", "animal de estimação", "animal", "doméstico", "companheiro", "família"], "translation": {"es": "mascota", "en": "pet", "fr": "animal de compagnie", "de": "Haustier", "it": "animale domestico", "pt": "animal de estimação"}},
    {"num": 30, "id": 3730, "traditional": "單身", "simplified": "单身", "pinyin": "dānshēn", "zhuyin": "ㄉㄢ ㄕㄣ", "type": "Vs", "tags": ["soltero", "estado civil", "relación", "persona", "adjetivo", "single", "unmarried", "relationship status", "person", "adjective", "célibataire", "état civil", "relation", "personne", "adjectif", "Single", "ledig", "Familienstand", "Person", "Adjektiv", "single", "stato civile", "relazione", "persona", "aggettivo", "solteiro", "estado civil", "relacionamento", "pessoa", "adjetivo"], "translation": {"es": "ser soltero", "en": "to be single", "fr": "être célibataire", "de": "Single sein", "it": "essere single", "pt": "ser solteiro"}},
    {"num": 31, "id": 3731, "traditional": "醫院", "simplified": "医院", "pinyin": "yīyuàn", "zhuyin": "ㄧ ㄩㄢˋ", "type": "N", "tags": ["hospital", "salud", "médico", "lugar", "edificio", "hospital", "health", "medical", "place", "building", "hôpital", "santé", "médical", "lieu", "bâtiment", "Krankenhaus", "Gesundheit", "medizinisch", "Ort", "Gebäude", "ospedale", "salute", "medico", "luogo", "edificio", "hospital", "saúde", "médico", "lugar", "prédio"], "translation": {"es": "hospital", "en": "hospital", "fr": "hôpital", "de": "Krankenhaus", "it": "ospedale", "pt": "hospital"}},
    {"num": 32, "id": 3732, "traditional": "意見", "simplified": "意见", "pinyin": "yìjiàn", "zhuyin": "ㄧˋ ㄐㄧㄢˋ", "type": "N", "tags": ["opinión", "sugerencia", "idea", "punto de vista", "consejo", "opinion", "suggestion", "idea", "viewpoint", "advice", "opinion", "suggestion", "idée", "point de vue", "conseil", "Meinung", "Vorschlag", "Idee", "Standpunkt", "Ratschlag", "opinione", "suggerimento", "idea", "punto di vista", "consiglio", "opinião", "sugestão", "ideia", "ponto de vista", "conselho"], "translation": {"es": "sugerencia, opinión", "en": "suggestion, opinion", "fr": "suggestion, opinion", "de": "Vorschlag, Meinung", "it": "suggerimento, opinione", "pt": "sugestão, opinião"}},
    {"num": 33, "id": 3733, "traditional": "建立", "simplified": "建立", "pinyin": "jiànlì", "zhuyin": "ㄐㄧㄢˋ ㄌㄧˋ", "type": "V", "tags": ["acción", "establecer", "fundar", "crear", "organización", "action", "to establish", "to found", "to create", "organization", "action", "établir", "fonder", "créer", "organisation", "Aktion", "gründen", "errichten", "schaffen", "Organisation", "azione", "stabilire", "fondare", "creare", "organizzazione", "ação", "estabelecer", "fundar", "criar", "organização"], "translation": {"es": "establecer", "en": "to establish", "fr": "établir", "de": "gründen, errichten", "it": "stabilire", "pt": "estabelecer"}},
    {"num": 34, "id": 3734, "traditional": "散步", "simplified": "散步", "pinyin": "sànbù", "zhuyin": "ㄙㄢˋ ㄅㄨˋ", "type": "V-sep", "tags": ["acción", "pasear", "caminar", "ocio", "actividad", "action", "to take a walk", "to stroll", "leisure", "activity", "action", "se promener", "flâner", "loisir", "activité", "Aktion", "spazieren gehen", "bummeln", "Freizeit", "Aktivität", "azione", "fare una passeggiata", "passeggiare", "svago", "attività", "ação", "dar um passeio", "caminhar", "lazer", "atividade"], "translation": {"es": "dar un paseo", "en": "to take a walk", "fr": "se promener", "de": "spazieren gehen", "it": "fare una passeggiata", "pt": "dar um passeio"}},
    {"num": 35, "id": 3735, "traditional": "家庭", "simplified": "家庭", "pinyin": "jiātíng", "zhuyin": "ㄐㄧㄚ ㄊㄧㄥˊ", "type": "N", "tags": ["familia", "hogar", "parientes", "unidad", "social", "family", "household", "relatives", "unit", "social", "famille", "foyer", "parents", "unité", "social", "Familie", "Haushalt", "Verwandte", "Einheit", "sozial", "famiglia", "nucleo familiare", "parenti", "unità", "sociale", "família", "lar", "parentes", "unidade", "social"], "translation": {"es": "familia", "en": "family", "fr": "famille", "de": "Familie", "it": "famiglia", "pt": "família"}},
    {"num": 36, "id": 3736, "traditional": "真正", "simplified": "真正", "pinyin": "zhēnzhèng", "zhuyin": "ㄓㄣ ㄓㄥˋ", "type": "Vs-attr", "tags": ["real", "verdadero", "genuino", "auténtico", "adjetivo", "real", "true", "genuine", "authentic", "adjective", "réel", "vrai", "véritable", "authentique", "adjectif", "wirklich", "wahr", "echt", "authentisch", "Adjektiv", "reale", "vero", "genuino", "autentico", "aggettivo", "real", "verdadeiro", "genuíno", "autêntico", "adjetivo"], "translation": {"es": "real, verdadero, genuino", "en": "real, true, genuine", "fr": "réel, vrai, authentique", "de": "wirklich, echt", "it": "reale, vero, genuino", "pt": "real, verdadeiro, genuíno"}},
    {"num": 37, "id": 3737, "traditional": "幸福", "simplified": "幸福", "pinyin": "xìngfú", "zhuyin": "ㄒㄧㄥˋ ㄈㄨˊ", "type": "N", "tags": ["felicidad", "bendición", "alegría", "sentimiento", "positivo", "happiness", "blessing", "joy", "feeling", "positive", "bonheur", "bénédiction", "joie", "sentiment", "positif", "Glück", "Segen", "Freude", "Gefühl", "positiv", "felicità", "benedizione", "gioia", "sentimento", "positivo", "felicidade", "bênção", "alegria", "sentimento", "positivo"], "translation": {"es": "felicidad, bendición", "en": "happiness, blessing", "fr": "bonheur, bénédiction", "de": "Glück, Segen", "it": "felicità, benedizione", "pt": "felicidade, bênção"}},
    {"num": 38, "id": 3738, "traditional": "跌倒", "simplified": "跌倒", "pinyin": "dié dǎo", "zhuyin": "ㄉㄧㄝˊ ㄉㄠˇ", "type": "Phrases", "tags": ["acción", "caerse", "accidente", "tropezar", "cuerpo", "action", "to fall down", "accident", "to stumble", "body", "action", "tomber", "accident", "trébucher", "corps", "Aktion", "hinfallen", "Unfall", "stolpern", "Körper", "azione", "cadere", "incidente", "inciampare", "corpo", "ação", "cair", "acidente", "tropeçar", "corpo"], "translation": {"es": "caerse", "en": "to fall down", "fr": "tomber", "de": "hinfallen", "it": "cadere", "pt": "cair"}},
    {"num": 39, "id": 3739, "traditional": "當成", "simplified": "当成", "pinyin": "dàng chéng", "zhuyin": "ㄉㄤˋ ㄔㄥˊ", "type": "Phrases", "tags": ["considerar como", "ver como", "tratar como", "verbo", "percepción", "to consider as", "to view as", "to regard as", "verb", "perception", "considérer comme", "voir comme", "traiter comme", "verbe", "perception", "betrachten als", "ansehen als", "behandeln als", "Verb", "Wahrnehmung", "considerare come", "vedere come", "trattare come", "verbo", "percezione", "considerar como", "ver como", "tratar como", "verbo", "percepção"], "translation": {"es": "considerar como, ver como", "en": "to consider, view as, regard as", "fr": "considérer comme", "de": "betrachten als", "it": "considerare come", "pt": "considerar como"}},
    {"num": 40, "id": 3740, "traditional": "忍不住", "simplified": "忍不住", "pinyin": "rěn bú zhù", "zhuyin": "ㄖㄣˇ ㄅㄨˊ ㄓㄨˋ", "type": "Phrases", "tags": ["no poder evitar", "inaguantable", "límite", "sentimiento", "expresión", "to be beyond the limits of endurance", "can't help but", "unbearable", "limit", "feeling", "ne pas pouvoir s'empêcher de", "insupportable", "limite", "sentiment", "expression", "nicht umhin können", "unerträglich", "Grenze", "Gefühl", "Ausdruck", "non poter fare a meno di", "insopportabile", "limite", "sentimento", "espressione", "não conseguir evitar", "insuportável", "limite", "sentimento", "expressão"], "translation": {"es": "no poder aguantar", "en": "to be beyond the limits of endurance", "fr": "ne pas pouvoir s'empêcher de", "de": "nicht umhin können", "it": "non poterne più", "pt": "não conseguir aguentar"}}
]
