[
    {"num": 1, "id": 11401, "traditional": "單位", "simplified": "单位", "pinyin": "dānwèi", "zhuyin": "ㄉㄢ ㄨㄟˋ", "type": "N", "tags": ["unidad", "medida", "estándar", "unit", "measure", "standard", "unité", "mesure", "standard", "Einheit", "Maß", "Standard", "unità", "misura", "standard", "unidade", "medida", "padrão"], "translation": {"es": "unidad (de medida)", "en": "unit (of measurement)", "fr": "unité (de mesure)", "de": "Einheit (Maßeinheit)", "it": "unità (di misura)", "pt": "unidade (de medida)"}},
    {"num": 2, "id": 11402, "traditional": "公分", "simplified": "公分", "pinyin": "gōngfēn", "zhuyin": "ㄍㄨㄥ ㄈㄣ", "type": "M", "tags": ["centímetro", "medida", "longitud", "métrico", "Taiwán", "centimeter", "measure", "length", "metric", "Taiwan", "centimètre", "mesure", "longueur", "métrique", "Taïwan", "Zentimeter", "Maß", "Länge", "metrisch", "Taiwan", "centimetro", "misura", "lunghezza", "metrico", "Taiwan", "centímetro", "medida", "comprimento", "métrico", "Taiwan"], "translation": {"es": "centímetro", "en": "centimeter", "fr": "centimètre", "de": "Zentimeter", "it": "centimetro", "pt": "centímetro"}},
    {"num": 3, "id": 11403, "traditional": "公尺", "simplified": "公尺", "pinyin": "gōngchǐ", "zhuyin": "ㄍㄨㄥ ㄔˇ", "type": "M", "tags": ["metro", "medida", "longitud", "métrico", "Taiwán", "meter", "measure", "length", "metric", "Taiwan", "mètre", "mesure", "longueur", "métrique", "Taïwan", "Meter", "Maß", "Länge", "metrisch", "Taiwan", "metro", "misura", "lunghezza", "metrico", "Taiwan", "metro", "medida", "comprimento", "métrico", "Taiwan"], "translation": {"es": "metro", "en": "meter", "fr": "mètre", "de": "Meter", "it": "metro", "pt": "metro"}},
    {"num": 4, "id": 11404, "traditional": "公里", "simplified": "公里", "pinyin": "gōnglǐ", "zhuyin": "ㄍㄨㄥ ㄌㄧˇ", "type": "M", "tags": ["kilómetro", "medida", "distancia", "métrico", "largo", "kilometer", "measure", "distance", "metric", "long", "kilomètre", "mesure", "distance", "métrique", "long", "Kilometer", "Maß", "Entfernung", "metrisch", "lang", "chilometro", "misura", "distanza", "metrico", "lungo", "quilômetro", "medida", "distância", "métrico", "longo"], "translation": {"es": "kilómetro", "en": "kilometer", "fr": "kilomètre", "de": "Kilometer", "it": "chilometro", "pt": "quilômetro"}},
    {"num": 5, "id": 11405, "traditional": "公克", "simplified": "公克", "pinyin": "gōngkè", "zhuyin": "ㄍㄨㄥ ㄎㄜˋ", "type": "M", "tags": ["gramo", "medida", "peso", "métrico", "Taiwán", "gram", "measure", "weight", "metric", "Taiwan", "gramme", "mesure", "poids", "métrique", "Taïwan", "Gramm", "Maß", "Gewicht", "metrisch", "Taiwan", "grammo", "misura", "peso", "metrico", "Taiwan", "grama", "medida", "peso", "métrico", "Taiwan"], "translation": {"es": "gramo", "en": "gram", "fr": "gramme", "de": "Gramm", "it": "grammo", "pt": "grama"}},
    {"num": 6, "id": 11406, "traditional": "公斤", "simplified": "公斤", "pinyin": "gōngjīn", "zhuyin": "ㄍㄨㄥ ㄐㄧㄣ", "type": "M", "tags": ["kilogramo", "medida", "peso", "métrico", "Taiwán", "kilogram", "measure", "weight", "metric", "Taiwan", "kilogramme", "mesure", "poids", "métrique", "Taïwan", "Kilogramm", "Maß", "Gewicht", "metrisch", "Taiwan", "chilogrammo", "misura", "peso", "metrico", "Taiwan", "quilograma", "medida", "peso", "métrico", "Taiwan"], "translation": {"es": "kilogramo", "en": "kilogram", "fr": "kilogramme", "de": "Kilogramm", "it": "chilogrammo", "pt": "quilograma"}},
    {"num": 7, "id": 11407, "traditional": "斤", "simplified": "斤", "pinyin": "jīn", "zhuyin": "ㄐㄧㄣ", "type": "M", "tags": ["catty", "medida", "peso", "tradicional", "Taiwán", "catty", "measure", "weight", "traditional", "Taiwan", "catty", "mesure", "poids", "traditionnel", "Taïwan", "Jin", "Maß", "Gewicht", "traditionell", "Taiwan", "catty", "misura", "peso", "tradizionale", "Taiwan", "catty", "medida", "peso", "tradicional", "Taiwan"], "translation": {"es": "catty (unidad de peso, ~600g en Taiwán)", "en": "catty (unit of weight, ~600g in Taiwan)", "fr": "catty (unité de poids, ~600g à Taïwan)", "de": "Jin (Gewichtseinheit, ~600g in Taiwan)", "it": "catty (unità di peso, ~600g a Taiwan)", "pt": "catty (unidade de peso, ~600g em Taiwan)"}},
    {"num": 8, "id": 11408, "traditional": "公升", "simplified": "公升", "pinyin": "gōngshēng", "zhuyin": "ㄍㄨㄥ ㄕㄥ", "type": "M", "tags": ["litro", "medida", "volumen", "líquido", "métrico", "liter", "measure", "volume", "liquid", "metric", "litre", "mesure", "volume", "liquide", "métrique", "Liter", "Maß", "Volumen", "Flüssigkeit", "metrisch", "litro", "misura", "volume", "liquido", "metrico", "litro", "medida", "volume", "líquido", "métrico"], "translation": {"es": "litro", "en": "liter", "fr": "litre", "de": "Liter", "it": "litro", "pt": "litro"}},
    {"num": 9, "id": 11409, "traditional": "毫升", "simplified": "毫升", "pinyin": "háoshēng", "zhuyin": "ㄏㄠˊ ㄕㄥ", "type": "M", "tags": ["mililitro", "medida", "volumen", "líquido", "pequeño", "milliliter", "measure", "volume", "liquid", "small", "millilitre", "mesure", "volume", "liquide", "petit", "Milliliter", "Maß", "Volumen", "Flüssigkeit", "klein", "millilitro", "misura", "volume", "liquido", "piccolo", "mililitro", "medida", "volume", "líquido", "pequeno"], "translation": {"es": "mililitro", "en": "milliliter", "fr": "millilitre", "de": "Milliliter", "it": "millilitro", "pt": "mililitro"}},
    {"num": 10, "id": 11410, "traditional": "度", "simplified": "度", "pinyin": "dù", "zhuyin": "ㄉㄨˋ", "type": "M", "tags": ["grado", "temperatura", "ángulo", "medida", "clasificador", "degree", "temperature", "angle", "measure", "classifier", "degré", "température", "angle", "mesure", "classificateur", "Grad", "Temperatur", "Winkel", "Maß", "Klassifikator", "grado", "temperatura", "angolo", "misura", "classificatore", "grau", "temperatura", "ângulo", "medida", "classificador"], "translation": {"es": "grado", "en": "degree", "fr": "degré", "de": "Grad", "it": "grado", "pt": "grau"}},
    {"num": 11, "id": 11411, "traditional": "攝氏", "simplified": "摄氏", "pinyin": "Shèshì", "zhuyin": "ㄕㄜˋ ㄕˋ", "type": "N", "tags": ["Celsius", "temperatura", "escala", "medida", "ciencia", "Celsius", "temperature", "scale", "measure", "science", "Celsius", "température", "échelle", "mesure", "science", "Celsius", "Temperatur", "Skala", "Maß", "Wissenschaft", "Celsius", "temperatura", "scala", "misura", "scienza", "Celsius", "temperatura", "escala", "medida", "ciência"], "translation": {"es": "Celsius", "en": "Celsius", "fr": "Celsius", "de": "Celsius", "it": "Celsius", "pt": "Celsius"}},
    {"num": 12, "id": 11412, "traditional": "華氏", "simplified": "华氏", "pinyin": "Huáshì", "zhuyin": "ㄏㄨㄚˊ ㄕˋ", "type": "N", "tags": ["Fahrenheit", "temperatura", "escala", "medida", "imperial", "Fahrenheit", "temperature", "scale", "measure", "imperial", "Fahrenheit", "température", "échelle", "mesure", "impérial", "Fahrenheit", "Temperatur", "Skala", "Maß", "imperial", "Fahrenheit", "temperatura", "scala", "misura", "imperiale", "Fahrenheit", "temperatura", "escala", "medida", "imperial"], "translation": {"es": "Fahrenheit", "en": "Fahrenheit", "fr": "Fahrenheit", "de": "Fahrenheit", "it": "Fahrenheit", "pt": "Fahrenheit"}},
    {"num": 13, "id": 11413, "traditional": "坪", "simplified": "坪", "pinyin": "píng", "zhuyin": "ㄆㄧㄥˊ", "type": "M", "tags": ["ping", "medida", "área", "tradicional", "Taiwán", "ping", "measure", "area", "traditional", "Taiwan", "ping", "mesure", "surface", "traditionnel", "Taïwan", "Ping", "Maß", "Fläche", "traditionell", "Taiwan", "ping", "misura", "area", "tradizionale", "Taiwan", "ping", "medida", "área", "tradicional", "Taiwan"], "translation": {"es": "ping (~3.3m²)", "en": "ping (~3.3m²)", "fr": "ping (~3.3m²)", "de": "Ping (~3,3m²)", "it": "ping (~3,3m²)", "pt": "ping (~3,3m²)"}},
    {"num": 14, "id": 11414, "traditional": "平方公尺", "simplified": "平方米", "pinyin": "píngfāng gōngchǐ", "zhuyin": "ㄆㄧㄥˊ ㄈㄤ ㄍㄨㄥ ㄔˇ", "type": "M", "tags": ["metro cuadrado", "medida", "área", "superficie", "métrico", "square meter", "measure", "area", "surface", "metric", "mètre carré", "mesure", "surface", "superficie", "métrique", "Quadratmeter", "Maß", "Fläche", "Oberfläche", "metrisch", "metro quadrato", "misura", "area", "superficie", "metrico", "metro quadrado", "medida", "área", "superfície", "métrico"], "translation": {"es": "metro cuadrado", "en": "square meter", "fr": "mètre carré", "de": "Quadratmeter", "it": "metro quadrato", "pt": "metro quadrado"}},
    {"num": 15, "id": 11415, "traditional": "吋", "simplified": "吋", "pinyin": "cùn", "zhuyin": "ㄘㄨㄣˋ", "type": "M", "tags": ["pulgada", "medida", "longitud", "imperial", "pantalla", "inch", "measure", "length", "imperial", "screen", "pouce", "mesure", "longueur", "impérial", "écran", "Zoll", "Maß", "Länge", "imperial", "Bildschirm", "pollice", "misura", "lunghezza", "imperiale", "schermo", "polegada", "medida", "comprimento", "imperial", "tela"], "translation": {"es": "pulgada", "en": "inch", "fr": "pouce", "de": "Zoll", "it": "pollice", "pt": "polegada"}},
    {"num": 16, "id": 11416, "traditional": "英尺", "simplified": "英尺", "pinyin": "yīngchǐ", "zhuyin": "ㄧㄥ ㄔˇ", "type": "M", "tags": ["pie", "medida", "longitud", "imperial", "altura", "foot", "measure", "length", "imperial", "height", "pied", "mesure", "longueur", "impérial", "hauteur", "Fuß", "Maß", "Länge", "imperial", "Höhe", "piede", "misura", "lunghezza", "imperiale", "altezza", "pé", "medida", "comprimento", "imperial", "altura"], "translation": {"es": "pie (medida)", "en": "foot (measurement)", "fr": "pied (mesure)", "de": "Fuß (Maß)", "it": "piede (misura)", "pt": "pé (medida)"}},
    {"num": 17, "id": 11417, "traditional": "碼", "simplified": "码", "pinyin": "mǎ", "zhuyin": "ㄇㄚˇ", "type": "M", "tags": ["yarda", "medida", "longitud", "imperial", "deporte", "yard", "measure", "length", "imperial", "sport", "yard", "mesure", "longueur", "impérial", "sport", "Yard", "Maß", "Länge", "imperial", "Sport", "iarda", "misura", "lunghezza", "imperiale", "sport", "jarda", "medida", "comprimento", "imperial", "esporte"], "translation": {"es": "yarda", "en": "yard", "fr": "yard", "de": "Yard", "it": "iarda", "pt": "jarda"}},
    {"num": 18, "id": 11418, "traditional": "英里", "simplified": "英里", "pinyin": "yīnglǐ", "zhuyin": "ㄧㄥ ㄌㄧˇ", "type": "M", "tags": ["milla", "medida", "distancia", "imperial", "largo", "mile", "measure", "distance", "imperial", "long", "mile", "mille", "mesure", "distance", "impérial", "long", "Meile", "Maß", "Entfernung", "imperial", "lang", "miglio", "misura", "distanza", "imperiale", "lungo", "milha", "medida", "distância", "imperial", "longo"], "translation": {"es": "milla", "en": "mile", "fr": "mile", "de": "Meile", "it": "miglio", "pt": "milha"}},
    {"num": 19, "id": 11419, "traditional": "加侖", "simplified": "加仑", "pinyin": "jiālún", "zhuyin": "ㄐㄧㄚ ㄌㄨㄣˊ", "type": "M", "tags": ["galón", "medida", "volumen", "líquido", "imperial", "gallon", "measure", "volume", "liquid", "imperial", "gallon", "mesure", "volume", "liquide", "impérial", "Gallone", "Maß", "Volumen", "Flüssigkeit", "imperial", "gallone", "misura", "volume", "liquido", "imperiale", "galão", "medida", "volume", "líquido", "imperial"], "translation": {"es": "galón", "en": "gallon", "fr": "gallon", "de": "Gallone", "it": "gallone", "pt": "galão"}},
    {"num": 20, "id": 11420, "traditional": "噸", "simplified": "吨", "pinyin": "dūn", "zhuyin": "ㄉㄨㄣ", "type": "M", "tags": ["tonelada", "medida", "peso", "métrico", "grande", "ton", "tonne", "measure", "weight", "metric", "large", "tonne", "mesure", "poids", "métrique", "grand", "Tonne", "Maß", "Gewicht", "metrisch", "groß", "tonnellata", "misura", "peso", "metrico", "grande", "tonelada", "medida", "peso", "métrico", "grande"], "translation": {"es": "tonelada", "en": "ton", "fr": "tonne", "de": "Tonne", "it": "tonnellata", "pt": "tonelada"}},
    {"num": 21, "id": 11421, "traditional": "尺寸", "simplified": "尺寸", "pinyin": "chǐcùn", "zhuyin": "ㄔˇ ㄘㄨㄣˋ", "type": "N", "tags": ["dimensión", "tamaño", "medida", "longitud", "ropa", "dimension", "size", "measurement", "length", "clothing", "dimension", "taille", "mesure", "longueur", "vêtements", "Abmessung", "Größe", "Maß", "Länge", "Kleidung", "dimensione", "taglia", "misura", "lunghezza", "abbigliamento", "dimensão", "tamanho", "medida", "comprimento", "roupa"], "translation": {"es": "dimensiones, tamaño", "en": "size, dimensions", "fr": "dimensions, taille", "de": "Größe, Abmessungen", "it": "dimensioni, taglia", "pt": "dimensões, tamanho"}},
    {"num": 22, "id": 11422, "traditional": "測量", "simplified": "测量", "pinyin": "cèliáng", "zhuyin": "ㄘㄜˋ ㄌㄧㄤˊ", "type": "V", "tags": ["acción", "medir", "herramienta", "ciencia", "cantidad", "action", "to measure", "tool", "science", "quantity", "action", "mesurer", "outil", "science", "quantité", "Aktion", "messen", "Werkzeug", "Wissenschaft", "Menge", "azione", "misurare", "strumento", "scienza", "quantità", "ação", "medir", "ferramenta", "ciência", "quantidade"], "translation": {"es": "medir", "en": "to measure", "fr": "mesurer", "de": "messen", "it": "misurare", "pt": "medir"}},
    {"num": 23, "id": 11423, "traditional": "身高", "simplified": "身高", "pinyin": "shēngāo", "zhuyin": "ㄕㄣ ㄍㄠ", "type": "N", "tags": ["altura corporal", "altura", "cuerpo", "medida", "persona", "body height", "height", "body", "measure", "person", "taille (corporelle)", "hauteur", "corps", "mesure", "personne", "Körpergröße", "Größe", "Körper", "Maß", "Person", "altezza (corporea)", "corpo", "misura", "persona", "altura (corporal)", "corpo", "medida", "pessoa"], "translation": {"es": "estatura", "en": "height (of a person)", "fr": "taille (d'une personne)", "de": "Körpergröße", "it": "altezza (di una persona)", "pt": "altura (de uma pessoa)"}},
    {"num": 24, "id": 11424, "traditional": "體重", "simplified": "体重", "pinyin": "tǐzhòng", "zhuyin": "ㄊㄧˇ ㄓㄨㄥˋ", "type": "N", "tags": ["peso corporal", "peso", "cuerpo", "medida", "salud", "body weight", "weight", "body", "measure", "health", "poids corporel", "poids", "corps", "mesure", "santé", "Körpergewicht", "Gewicht", "Körper", "Maß", "Gesundheit", "peso corporeo", "peso", "corpo", "misura", "salute", "peso corporal", "peso", "corpo", "medida", "saúde"], "translation": {"es": "peso corporal", "en": "body weight", "fr": "poids corporel", "de": "Körpergewicht", "it": "peso corporeo", "pt": "peso corporal"}},
    {"num": 25, "id": 11425, "traditional": "體溫", "simplified": "体温", "pinyin": "tǐwēn", "zhuyin": "ㄊㄧˇ ㄨㄣ", "type": "N", "tags": ["temperatura corporal", "temperatura", "cuerpo", "salud", "fiebre", "body temperature", "temperature", "body", "health", "fever", "température corporelle", "température", "corps", "santé", "fièvre", "Körpertemperatur", "Temperatur", "Körper", "Gesundheit", "Fieber", "temperatura corporea", "temperatura", "corpo", "salute", "febbre", "temperatura corporal", "temperatura", "corpo", "saúde", "febre"], "translation": {"es": "temperatura corporal", "en": "body temperature", "fr": "température corporelle", "de": "Körpertemperatur", "it": "temperatura corporea", "pt": "temperatura corporal"}},
    {"num": 26, "id": 11426, "traditional": "容量", "simplified": "容量", "pinyin": "róngliàng", "zhuyin": "ㄖㄨㄥˊ ㄌㄧㄤˋ", "type": "N", "tags": ["capacidad", "volumen", "medida", "líquido", "recipiente", "capacity", "volume", "measure", "liquid", "container", "capacité", "volume", "mesure", "liquide", "récipient", "Fassungsvermögen", "Kapazität", "Volumen", "Maß", "Flüssigkeit", "Behälter", "capacità", "volume", "misura", "liquido", "contenitore", "capacidade", "volume", "medida", "líquido", "recipiente"], "translation": {"es": "capacidad, volumen", "en": "capacity, volume", "fr": "capacité, volume", "de": "Kapazität, Volumen", "it": "capacità, volume", "pt": "capacidade, volume"}},
    {"num": 27, "id": 11427, "traditional": "速度", "simplified": "速度", "pinyin": "sùdù", "zhuyin": "ㄙㄨˋ ㄉㄨˋ", "type": "N", "tags": ["velocidad", "rapidez", "medida", "movimiento", "distancia", "speed", "velocity", "measure", "movement", "distance", "vitesse", "rapidité", "mesure", "mouvement", "distance", "Geschwindigkeit", "Schnelligkeit", "Maß", "Bewegung", "Entfernung", "velocità", "rapidità", "misura", "movimento", "distanza", "velocidade", "rapidez", "medida", "movimento", "distância"], "translation": {"es": "velocidad", "en": "speed", "fr": "vitesse", "de": "Geschwindigkeit", "it": "velocità", "pt": "velocidade"}},
    {"num": 28, "id": 11428, "traditional": "深度", "simplified": "深度", "pinyin": "shēndù", "zhuyin": "ㄕㄣ ㄉㄨˋ", "type": "N", "tags": ["profundidad", "medida", "distancia", "agua", "vertical", "depth", "measure", "distance", "water", "vertical", "profondeur", "mesure", "distance", "eau", "vertical", "Tiefe", "Maß", "Entfernung", "Wasser", "vertikal", "profondità", "misura", "distanza", "acqua", "verticale", "profundidade", "medida", "distância", "água", "vertical"], "translation": {"es": "profundidad", "en": "depth", "fr": "profondeur", "de": "Tiefe", "it": "profondità", "pt": "profundidade"}},
    {"num": 29, "id": 11429, "traditional": "寬度", "simplified": "宽度", "pinyin": "kuāndù", "zhuyin": "ㄎㄨㄢ ㄉㄨˋ", "type": "N", "tags": ["anchura", "ancho", "medida", "distancia", "horizontal", "width", "breadth", "measure", "distance", "horizontal", "largeur", "mesure", "distance", "horizontal", "Breite", "Weite", "Maß", "Entfernung", "horizontal", "larghezza", "misura", "distanza", "orizzontale", "largura", "medida", "distância", "horizontal"], "translation": {"es": "anchura", "en": "width", "fr": "largeur", "de": "Breite", "it": "larghezza", "pt": "largura"}},
    {"num": 30, "id": 11430, "traditional": "長度", "simplified": "长度", "pinyin": "chángdù", "zhuyin": "ㄔㄤˊ ㄉㄨˋ", "type": "N", "tags": ["longitud", "largo", "medida", "distancia", "horizontal", "length", "measure", "distance", "horizontal", "dimension", "longueur", "mesure", "distance", "horizontal", "dimension", "Länge", "Maß", "Entfernung", "horizontal", "Abmessung", "lunghezza", "misura", "distanza", "orizzontale", "dimensione", "comprimento", "medida", "distância", "horizontal", "dimensão"], "translation": {"es": "longitud", "en": "length", "fr": "longueur", "de": "Länge", "it": "lunghezza", "pt": "comprimento"}},
    {"num": 31, "id": 11431, "traditional": "高度", "simplified": "高度", "pinyin": "gāodù", "zhuyin": "ㄍㄠ ㄉㄨˋ", "type": "N", "tags": ["altura", "elevación", "medida", "distancia", "vertical", "height", "altitude", "elevation", "measure", "distance", "vertical", "hauteur", "altitude", "élévation", "mesure", "distance", "vertical", "Höhe", "Maß", "Entfernung", "vertikal", "altezza", "altitudine", "elevazione", "misura", "distanza", "verticale", "altura", "altitude", "elevação", "medida", "distância", "vertical"], "translation": {"es": "altura", "en": "height", "fr": "hauteur", "de": "Höhe", "it": "altezza", "pt": "altura"}},
    {"num": 32, "id": 11432, "traditional": "數量", "simplified": "数量", "pinyin": "shùliàng", "zhuyin": "ㄕㄨˋ ㄌㄧㄤˋ", "type": "N", "tags": ["cantidad", "número", "medida", "magnitud", "total", "quantity", "amount", "number", "measure", "total", "quantité", "montant", "nombre", "mesure", "total", "Menge", "Anzahl", "Zahl", "Maß", "Gesamt", "quantità", "ammontare", "numero", "misura", "totale", "quantidade", "montante", "número", "medida", "total"], "translation": {"es": "cantidad", "en": "quantity", "fr": "quantité", "de": "Menge", "it": "quantità", "pt": "quantidade"}},
    {"num": 33, "id": 11433, "traditional": "距離", "simplified": "距离", "pinyin": "jùlí", "zhuyin": "ㄐㄩˋ ㄌㄧˊ", "type": "N", "tags": ["distancia", "espacio", "lejanía", "medida", "separación", "distance", "space", "remoteness", "measure", "separation", "distance", "espace", "éloignement", "mesure", "séparation", "Entfernung", "Abstand", "Raum", "Ferne", "Maß", "distanza", "spazio", "lontananza", "misura", "separazione", "distância", "espaço", "lonjura", "medida", "separação"], "translation": {"es": "distancia", "en": "distance", "fr": "distance", "de": "Entfernung", "it": "distanza", "pt": "distância"}},
    {"num": 34, "id": 11434, "traditional": "大小", "simplified": "大小", "pinyin": "dàxiǎo", "zhuyin": "ㄉㄚˋ ㄒㄧㄠˇ", "type": "N", "tags": ["tamaño", "dimensión", "medida", "grande", "pequeño", "size", "dimension", "measurement", "big", "small", "taille", "dimension", "mesure", "grand", "petit", "Größe", "Abmessung", "Maß", "groß", "klein", "dimensione", "taglia", "misura", "grande", "piccolo", "tamanho", "dimensão", "medida", "grande", "pequeno"], "translation": {"es": "tamaño", "en": "size", "fr": "taille", "de": "Größe", "it": "dimensione", "pt": "tamanho"}},
    {"num": 35, "id": 11435, "traditional": "公噸", "simplified": "公吨", "pinyin": "gōngdūn", "zhuyin": "ㄍㄨㄥ ㄉㄨㄣ", "type": "M", "tags": ["tonelada métrica", "tonelada", "peso", "medida", "grande", "metric ton", "tonne", "weight", "measure", "large", "tonne métrique", "tonne", "poids", "mesure", "grand", "metrische Tonne", "Tonne", "Gewicht", "Maß", "groß", "tonnellata metrica", "tonnellata", "peso", "misura", "grande", "tonelada métrica", "tonelada", "peso", "medida", "grande"], "translation": {"es": "tonelada métrica", "en": "metric ton", "fr": "tonne métrique", "de": "metrische Tonne", "it": "tonnellata metrica", "pt": "tonelada métrica"}},
    {"num": 36, "id": 11436, "traditional": "尺", "simplified": "尺", "pinyin": "chǐ", "zhuyin": "ㄔˇ", "type": "N", "tags": ["regla", "herramienta", "medir", "longitud", "instrumento", "ruler", "tool", "to measure", "length", "instrument", "règle", "outil", "mesurer", "longueur", "instrument", "Lineal", "Werkzeug", "messen", "Länge", "Instrument", "righello", "strumento", "misurare", "lunghezza", "strumento", "régua", "ferramenta", "medir", "comprimento", "instrumento"], "translation": {"es": "regla", "en": "ruler", "fr": "règle", "de": "Lineal", "it": "righello", "pt": "régua"}},
    {"num": 37, "id": 11437, "traditional": "磅", "simplified": "磅", "pinyin": "bàng", "zhuyin": "ㄅㄤˋ", "type": "M", "tags": ["libra", "peso", "medida", "imperial", "comida", "pound", "weight", "measure", "imperial", "food", "livre", "poids", "mesure", "impérial", "nourriture", "Pfund", "Gewicht", "Maß", "imperial", "Essen", "libbra", "peso", "misura", "imperiale", "cibo", "libra", "peso", "medida", "imperial", "comida"], "translation": {"es": "libra (peso)", "en": "pound (weight)", "fr": "livre (poids)", "de": "Pfund", "it": "libbra", "pt": "libra"}},
    {"num": 38, "id": 11438, "traditional": "盎司", "simplified": "盎司", "pinyin": "àngsī", "zhuyin": "ㄤˋ ㄙ", "type": "M", "tags": ["onza", "peso", "volumen", "medida", "imperial", "ounce", "weight", "volume", "measure", "imperial", "once", "poids", "volume", "mesure", "impérial", "Unze", "Gewicht", "Volumen", "Maß", "imperial", "oncia", "peso", "volume", "misura", "imperiale", "onça", "peso", "volume", "medida", "imperial"], "translation": {"es": "onza", "en": "ounce", "fr": "once", "de": "Unze", "it": "oncia", "pt": "onça"}},
    {"num": 39, "id": 11439, "traditional": "公頃", "simplified": "公顷", "pinyin": "gōngqǐng", "zhuyin": "ㄍㄨㄥ ㄑㄧㄥˇ", "type": "M", "tags": ["hectárea", "área", "superficie", "tierra", "métrico", "hectare", "area", "surface", "land", "metric", "hectare", "surface", "superficie", "terre", "métrique", "Hektar", "Fläche", "Oberfläche", "Land", "metrisch", "ettaro", "area", "superficie", "terreno", "metrico", "hectare", "área", "superfície", "terra", "métrico"], "translation": {"es": "hectárea", "en": "hectare", "fr": "hectare", "de": "Hektar", "it": "ettaro", "pt": "hectare"}},
    {"num": 40, "id": 11440, "traditional": "毫米", "simplified": "毫米", "pinyin": "háomǐ", "zhuyin": "ㄏㄠˊ ㄇㄧˇ", "type": "M", "tags": ["milímetro", "medida", "longitud", "métrico", "pequeño", "millimeter", "measure", "length", "metric", "small", "millimètre", "mesure", "longueur", "métrique", "petit", "Millimeter", "Maß", "Länge", "metrisch", "klein", "millimetro", "misura", "lunghezza", "metrico", "piccolo", "milímetro", "medida", "comprimento", "métrico", "pequeno"], "translation": {"es": "milímetro", "en": "millimeter", "fr": "millimètre", "de": "Millimeter", "it": "millimetro", "pt": "milímetro"}},
    {"num": 41, "id": 11441, "traditional": "比例", "simplified": "比例", "pinyin": "bǐlì", "zhuyin": "ㄅㄧˇ ㄌㄧˋ", "type": "N", "tags": ["proporción", "escala", "relación", "matemáticas", "comparación", "proportion", "ratio", "scale", "relationship", "math", "proportion", "rapport", "échelle", "relation", "mathématiques", "Verhältnis", "Proportion", "Maßstab", "Beziehung", "Mathematik", "proporzione", "rapporto", "scala", "relazione", "matematica", "proporção", "razão", "escala", "relação", "matemática"], "translation": {"es": "proporción, escala", "en": "proportion, scale", "fr": "proportion, échelle", "de": "Verhältnis, Maßstab", "it": "proporzione, scala", "pt": "proporção, escala"}},
    {"num": 42, "id": 11442, "traditional": "百分比", "simplified": "百分比", "pinyin": "bǎifēnbǐ", "zhuyin": "ㄅㄞˇ ㄈㄣ ㄅㄧˇ", "type": "N", "tags": ["porcentaje", "proporción", "matemáticas", "estadística", "cien", "percentage", "proportion", "math", "statistics", "hundred", "pourcentage", "proportion", "mathématiques", "statistiques", "cent", "Prozentsatz", "Verhältnis", "Mathematik", "Statistik", "hundert", "percentuale", "proporzione", "matematica", "statistica", "cento", "porcentagem", "proporção", "matemática", "estatística", "cem"], "translation": {"es": "porcentaje", "en": "percentage", "fr": "pourcentage", "de": "Prozentsatz", "it": "percentuale", "pt": "porcentagem"}},
    {"num": 43, "id": 11443, "traditional": "體積", "simplified": "体积", "pinyin": "tǐjī", "zhuyin": "ㄊㄧˇ ㄐㄧ", "type": "N", "tags": ["volumen", "espacio", "medida", "tres dimensiones", "física", "volume", "space", "measurement", "three-dimensional", "physics", "volume", "espace", "mesure", "trois dimensions", "physique", "Volumen", "Raum", "Maß", "dreidimensional", "Physik", "volume", "spazio", "misura", "tridimensionale", "fisica", "volume", "espaço", "medida", "tridimensional", "física"], "translation": {"es": "volumen", "en": "volume", "fr": "volume", "de": "Volumen", "it": "volume", "pt": "volume"}},
    {"num": 44, "id": 11444, "traditional": "瓦特", "simplified": "瓦特", "pinyin": "wǎtè", "zhuyin": "ㄨㄚˇ ㄊㄜˋ", "type": "M", "tags": ["vatio", "potencia", "electricidad", "medida", "ciencia", "watt", "power", "electricity", "measure", "science", "watt", "puissance", "électricité", "mesure", "science", "Watt", "Leistung", "Elektrizität", "Maß", "Wissenschaft", "watt", "potenza", "elettricità", "misura", "scienza", "watt", "potência", "eletricidade", "medida", "ciência"], "translation": {"es": "vatio", "en": "watt", "fr": "watt", "de": "Watt", "it": "watt", "pt": "watt"}},
    {"num": 45, "id": 11445, "traditional": "伏特", "simplified": "伏特", "pinyin": "fútè", "zhuyin": "ㄈㄨˊ ㄊㄜˋ", "type": "M", "tags": ["voltio", "voltaje", "electricidad", "medida", "ciencia", "volt", "voltage", "electricity", "measure", "science", "volt", "tension", "électricité", "mesure", "science", "Volt", "Spannung", "Elektrizität", "Maß", "Wissenschaft", "volt", "tensione", "elettricità", "misura", "scienza", "volt", "voltagem", "eletricidade", "medida", "ciência"], "translation": {"es": "voltio", "en": "volt", "fr": "volt", "de": "Volt", "it": "volt", "pt": "volt"}},
    {"num": 46, "id": 11446, "traditional": "安培", "simplified": "安培", "pinyin": "ānpéi", "zhuyin": "ㄢ ㄆㄟˊ", "type": "M", "tags": ["amperio", "corriente", "electricidad", "medida", "ciencia", "ampere", "current", "electricity", "measure", "science", "ampère", "courant", "électricité", "mesure", "science", "Ampere", "Strom", "Elektrizität", "Maß", "Wissenschaft", "ampere", "corrente", "elettricità", "misura", "scienza", "ampere", "corrente", "eletricidade", "medida", "ciência"], "translation": {"es": "amperio", "en": "ampere", "fr": "ampère", "de": "Ampere", "it": "ampere", "pt": "ampere"}},
    {"num": 47, "id": 11447, "traditional": "卡路里", "simplified": "卡路里", "pinyin": "kǎlùlǐ", "zhuyin": "ㄎㄚˇ ㄌㄨˋ ㄌㄧˇ", "type": "N", "tags": ["caloría", "energía", "comida", "dieta", "salud", "calorie", "energy", "food", "diet", "health", "calorie", "énergie", "nourriture", "régime", "santé", "Kalorie", "Energie", "Essen", "Diät", "Gesundheit", "caloria", "energia", "cibo", "dieta", "salute", "caloria", "energia", "comida", "dieta", "saúde"], "translation": {"es": "caloría", "en": "calorie", "fr": "calorie", "de": "Kalorie", "it": "caloria", "pt": "caloria"}},
    {"num": 48, "id": 11448, "traditional": "焦耳", "simplified": "焦耳", "pinyin": "jiāo'ěr", "zhuyin": "ㄐㄧㄠ ㄦˇ", "type": "M", "tags": ["julio", "energía", "trabajo", "física", "ciencia", "joule", "energy", "work", "physics", "science", "joule", "énergie", "travail", "physique", "science", "Joule", "Energie", "Arbeit", "Physik", "Wissenschaft", "joule", "energia", "lavoro", "fisica", "scienza", "joule", "energia", "trabalho", "física", "ciência"], "translation": {"es": "julio (unidad de energía)", "en": "joule", "fr": "joule", "de": "Joule", "it": "joule", "pt": "joule"}},
    {"num": 49, "id": 11449, "traditional": "赫茲", "simplified": "赫兹", "pinyin": "hèzī", "zhuyin": "ㄏㄜˋ ㄗ", "type": "M", "tags": ["hercio", "frecuencia", "sonido", "ondas", "ciencia", "hertz", "frequency", "sound", "waves", "science", "hertz", "fréquence", "son", "ondes", "science", "Hertz", "Frequenz", "Schall", "Wellen", "Wissenschaft", "hertz", "frequenza", "suono", "onde", "scienza", "hertz", "frequência", "som", "ondas", "ciência"], "translation": {"es": "hercio", "en": "hertz", "fr": "hertz", "de": "Hertz", "it": "hertz", "pt": "hertz"}},
    {"num": 50, "id": 11450, "traditional": "分貝", "simplified": "分贝", "pinyin": "fēnbèi", "zhuyin": "ㄈㄣ ㄅㄟˋ", "type": "M", "tags": ["decibelio", "sonido", "ruido", "intensidad", "medida", "decibel", "sound", "noise", "intensity", "measure", "décibel", "son", "bruit", "intensité", "mesure", "Dezibel", "Schall", "Lärm", "Intensität", "Maß", "decibel", "suono", "rumore", "intensità", "misura", "decibel", "som", "ruído", "intensidade", "medida"], "translation": {"es": "decibelio", "en": "decibel", "fr": "décibel", "de": "Dezibel", "it": "decibel", "pt": "decibel"}},
    {"num": 51, "id": 11451, "traditional": "毫克", "simplified": "毫克", "pinyin": "háokè", "zhuyin": "ㄏㄠˊ ㄎㄜˋ", "type": "M", "tags": ["miligramo", "medida", "peso", "pequeño", "métrico", "milligram", "measure", "weight", "small", "metric", "milligramme", "mesure", "poids", "petit", "métrique", "Milligramm", "Maß", "Gewicht", "klein", "metrisch", "milligrammo", "misura", "peso", "piccolo", "metrico", "miligrama", "medida", "peso", "pequeno", "métrico"], "translation": {"es": "miligramo", "en": "milligram", "fr": "milligramme", "de": "Milligramm", "it": "milligrammo", "pt": "miligrama"}}
]
