[
    {"num": 1, "id": 11301, "traditional": "運動", "simplified": "运动", "pinyin": "yùndòng", "zhuyin": "ㄩㄣˋ ㄉㄨㄥˋ", "type": "N", "tags": ["deporte", "ejercicio", "actividad", "salud", "sport", "exercise", "activity", "health", "sport", "exercice", "activité", "santé", "Sport", "Übung", "Aktivität", "Gesundheit", "sport", "esercizio", "attività", "salute", "esporte", "exercício", "atividade", "saúde"], "translation": {"es": "deporte, ejercicio", "en": "sports, exercise", "fr": "sport, exercice", "de": "Sport, Übung", "it": "sport, esercizio", "pt": "esporte, exercício"}},
    {"num": 2, "id": 11302, "traditional": "棒球", "simplified": "棒球", "pinyin": "bàngqiú", "zhuyin": "ㄅㄤˋ ㄑㄧㄡˊ", "type": "N", "tags": ["deporte", "béisbol", "juego de pelota", "equipo", "Taiwán", "sport", "baseball", "ball game", "team", "Taiwan", "sport", "baseball", "jeu de balle", "équipe", "Taïwan", "Sport", "Baseball", "Ballspiel", "Mannschaft", "Taiwan", "sport", "baseball", "gioco con la palla", "squadra", "Taiwan", "esporte", "beisebol", "jogo de bola", "equipe", "Taiwan"], "translation": {"es": "béisbol", "en": "baseball", "fr": "baseball", "de": "Baseball", "it": "baseball", "pt": "beisebol"}},
    {"num": 3, "id": 11303, "traditional": "籃球", "simplified": "篮球", "pinyin": "lánqiú", "zhuyin": "ㄌㄢˊ ㄑㄧㄡˊ", "type": "N", "tags": ["deporte", "baloncesto", "juego de pelota", "equipo", "cancha", "sport", "basketball", "ball game", "team", "court", "sport", "basket-ball", "jeu de balle", "équipe", "terrain", "Sport", "Basketball", "Ballspiel", "Mannschaft", "Feld", "sport", "pallacanestro", "gioco con la palla", "squadra", "campo", "esporte", "basquete", "jogo de bola", "equipe", "quadra"], "translation": {"es": "baloncesto", "en": "basketball", "fr": "basket-ball", "de": "Basketball", "it": "pallacanestro", "pt": "basquete"}},
    {"num": 4, "id": 11304, "traditional": "足球", "simplified": "足球", "pinyin": "zúqiú", "zhuyin": "ㄗㄨˊ ㄑㄧㄡˊ", "type": "N", "tags": ["deporte", "fútbol", "juego de pelota", "equipo", "campo", "sport", "soccer", "football", "ball game", "team", "field", "sport", "football", "jeu de balle", "équipe", "terrain", "Sport", "Fußball", "Ballspiel", "Mannschaft", "Feld", "sport", "calcio", "gioco con la palla", "squadra", "campo", "esporte", "futebol", "jogo de bola", "equipe", "campo"], "translation": {"es": "fútbol", "en": "soccer, football", "fr": "football", "de": "Fußball", "it": "calcio", "pt": "futebol"}},
    {"num": 5, "id": 11305, "traditional": "網球", "simplified": "网球", "pinyin": "wǎngqiú", "zhuyin": "ㄨㄤˇ ㄑㄧㄡˊ", "type": "N", "tags": ["deporte", "tenis", "juego de pelota", "raqueta", "cancha", "sport", "tennis", "ball game", "racket", "court", "sport", "tennis", "jeu de balle", "raquette", "court", "Sport", "Tennis", "Ballspiel", "Schläger", "Platz", "sport", "tennis", "gioco con la palla", "racchetta", "campo", "esporte", "tênis", "jogo de bola", "raquete", "quadra"], "translation": {"es": "tenis", "en": "tennis", "fr": "tennis", "de": "Tennis", "it": "tennis", "pt": "tênis"}},
    {"num": 6, "id": 11306, "traditional": "游泳", "simplified": "游泳", "pinyin": "yóuyǒng", "zhuyin": "ㄧㄡˊ ㄩㄥˇ", "type": "V", "tags": ["acción", "nadar", "deporte", "agua", "piscina", "action", "to swim", "sport", "water", "pool", "action", "nager", "sport", "eau", "piscine", "Aktion", "schwimmen", "Sport", "Wasser", "Schwimmbad", "azione", "nuotare", "sport", "acqua", "piscina", "ação", "nadar", "esporte", "água", "piscina"], "translation": {"es": "nadar", "en": "to swim", "fr": "nager", "de": "schwimmen", "it": "nuotare", "pt": "nadar"}},
    {"num": 7, "id": 11307, "traditional": "比賽", "simplified": "比赛", "pinyin": "bǐsài", "zhuyin": "ㄅㄧˇ ㄙㄞˋ", "type": "N", "tags": ["competencia", "partido", "juego", "evento", "deporte", "competition", "match", "game", "event", "sport", "compétition", "match", "jeu", "événement", "sport", "Wettbewerb", "Spiel", "Veranstaltung", "Sport", "competizione", "partita", "gioco", "evento", "sport", "competição", "partida", "jogo", "evento", "esporte"], "translation": {"es": "competición, partido", "en": "competition, match", "fr": "compétition, match", "de": "Wettbewerb, Spiel", "it": "competizione, partita", "pt": "competição, partida"}},
    {"num": 8, "id": 11308, "traditional": "選手", "simplified": "选手", "pinyin": "xuǎnshǒu", "zhuyin": "ㄒㄩㄢˇ ㄕㄡˇ", "type": "N", "tags": ["atleta", "jugador", "competidor", "persona", "deporte", "athlete", "player", "competitor", "person", "sport", "athlète", "joueur", "compétiteur", "personne", "sport", "Athlet", "Spieler", "Wettkämpfer", "Person", "Sport", "atleta", "giocatore", "concorrente", "persona", "sport", "atleta", "jogador", "competidor", "pessoa", "esporte"], "translation": {"es": "atleta, jugador", "en": "athlete, player", "fr": "athlète, joueur", "de": "Athlet, Spieler", "it": "atleta, giocatore", "pt": "atleta, jogador"}},
    {"num": 9, "id": 11309, "traditional": "教練", "simplified": "教练", "pinyin": "jiàoliàn", "zhuyin": "ㄐㄧㄠˋ ㄌㄧㄢˋ", "type": "N", "tags": ["entrenador", "profesión", "persona", "deporte", "equipo", "coach", "trainer", "profession", "person", "sport", "team", "entraîneur", "profession", "personne", "sport", "équipe", "Trainer", "Beruf", "Person", "Sport", "Mannschaft", "allenatore", "istruttore", "professione", "persona", "sport", "squadra", "treinador", "técnico", "profissão", "pessoa", "esporte", "equipe"], "translation": {"es": "entrenador", "en": "coach", "fr": "entraîneur", "de": "Trainer", "it": "allenatore", "pt": "treinador"}},
    {"num": 10, "id": 11310, "traditional": "隊伍", "simplified": "队伍", "pinyin": "duìwǔ", "zhuyin": "ㄉㄨㄟˋ ㄨˇ", "type": "N", "tags": ["equipo", "grupo", "deporte", "competición", "organización", "team", "squad", "group", "sport", "competition", "équipe", "groupe", "sport", "compétition", "organisation", "Mannschaft", "Team", "Gruppe", "Sport", "Wettbewerb", "squadra", "gruppo", "sport", "competizione", "organizzazione", "equipe", "time", "grupo", "esporte", "competição"], "translation": {"es": "equipo", "en": "team", "fr": "équipe", "de": "Mannschaft", "it": "squadra", "pt": "equipe"}},
    {"num": 11, "id": 11311, "traditional": "贏", "simplified": "赢", "pinyin": "yíng", "zhuyin": "ㄧㄥˊ", "type": "V", "tags": ["acción", "ganar", "victoria", "resultado", "positivo", "action", "to win", "victory", "result", "positive", "action", "gagner", "victoire", "résultat", "positif", "Aktion", "gewinnen", "Sieg", "Ergebnis", "positiv", "azione", "vincere", "vittoria", "risultato", "positivo", "ação", "ganhar", "vencer", "vitória", "resultado", "positivo"], "translation": {"es": "ganar", "en": "to win", "fr": "gagner", "de": "gewinnen", "it": "vincere", "pt": "ganhar"}},
    {"num": 12, "id": 11312, "traditional": "輸", "simplified": "输", "pinyin": "shū", "zhuyin": "ㄕㄨ", "type": "V", "tags": ["acción", "perder", "derrota", "resultado", "negativo", "action", "to lose", "defeat", "result", "negative", "action", "perdre", "défaite", "résultat", "négatif", "Aktion", "verlieren", "Niederlage", "Ergebnis", "negativ", "azione", "perdere", "sconfitta", "risultato", "negativo", "ação", "perder", "derrota", "resultado", "negativo"], "translation": {"es": "perder", "en": "to lose", "fr": "perdre", "de": "verlieren", "it": "perdere", "pt": "perder"}},
    {"num": 13, "id": 11313, "traditional": "打", "simplified": "打", "pinyin": "dǎ", "zhuyin": "ㄉㄚˇ", "type": "V", "tags": ["acción", "jugar con las manos", "golpear", "deporte", "pelota", "action", "to play (with hands)", "to hit", "sport", "ball", "action", "jouer (avec les mains)", "frapper", "sport", "balle", "Aktion", "spielen (mit Händen)", "schlagen", "Sport", "Ball", "azione", "giocare (con le mani)", "colpire", "sport", "palla", "ação", "jogar (com as mãos)", "bater", "esporte", "bola"], "translation": {"es": "jugar (deportes de mano)", "en": "to play (ball sports with hands)", "fr": "jouer (sports de main)", "de": "spielen (Ballsport mit Händen)", "it": "giocare (sport di mano)", "pt": "jogar (esportes com as mãos)"}},
    {"num": 14, "id": 11314, "traditional": "踢", "simplified": "踢", "pinyin": "tī", "zhuyin": "ㄊㄧ", "type": "V", "tags": ["acción", "patear", "fútbol", "deporte", "pie", "action", "to kick", "soccer", "sport", "foot", "action", "donner un coup de pied", "football", "sport", "pied", "Aktion", "treten", "Fußball", "Sport", "Fuß", "azione", "calciare", "calcio", "sport", "piede", "ação", "chutar", "futebol", "esporte", "pé"], "translation": {"es": "patear", "en": "to kick", "fr": "donner un coup de pied", "de": "treten", "it": "calciare", "pt": "chutar"}},
    {"num": 15, "id": 11315, "traditional": "跑", "simplified": "跑", "pinyin": "pǎo", "zhuyin": "ㄆㄠˇ", "type": "Vi", "tags": ["acción", "correr", "atletismo", "deporte", "movimiento", "action", "to run", "track and field", "sport", "movement", "action", "courir", "athlétisme", "sport", "mouvement", "Aktion", "laufen", "rennen", "Leichtathletik", "Sport", "Bewegung", "azione", "correre", "atletica", "sport", "movimento", "ação", "correr", "atletismo", "esporte", "movimento"], "translation": {"es": "correr", "en": "to run", "fr": "courir", "de": "laufen", "it": "correre", "pt": "correr"}},
    {"num": 16, "id": 11316, "traditional": "跳", "simplified": "跳", "pinyin": "tiào", "zhuyin": "ㄊㄧㄠˋ", "type": "Vi", "tags": ["acción", "saltar", "atletismo", "deporte", "movimiento", "action", "to jump", "track and field", "sport", "movement", "action", "sauter", "athlétisme", "sport", "mouvement", "Aktion", "springen", "Leichtathletik", "Sport", "Bewegung", "azione", "saltare", "atletica", "sport", "movimento", "ação", "pular", "saltar", "atletismo", "esporte", "movimento"], "translation": {"es": "saltar", "en": "to jump", "fr": "sauter", "de": "springen", "it": "saltare", "pt": "pular"}},
    {"num": 17, "id": 11317, "traditional": "冠軍", "simplified": "冠军", "pinyin": "guànjūn", "zhuyin": "ㄍㄨㄢˋ ㄐㄩㄣ", "type": "N", "tags": ["campeón", "ganador", "primer lugar", "competencia", "título", "champion", "winner", "first place", "competition", "title", "champion", "gagnant", "première place", "compétition", "titre", "Meister", "Sieger", "erster Platz", "Wettbewerb", "Titel", "campione", "vincitore", "primo posto", "competizione", "titolo", "campeão", "vencedor", "primeiro lugar", "competição", "título"], "translation": {"es": "campeón", "en": "champion", "fr": "champion", "de": "Meister", "it": "campione", "pt": "campeão"}},
    {"num": 18, "id": 11318, "traditional": "球場", "simplified": "球场", "pinyin": "qiúchǎng", "zhuyin": "ㄑㄧㄡˊ ㄔㄤˇ", "type": "N", "tags": ["cancha", "campo", "estadio", "deporte", "lugar", "court", "field", "stadium", "sport", "place", "terrain", "stade", "sport", "lieu", "Spielfeld", "Platz", "Stadion", "Sport", "Ort", "campo", "stadio", "sport", "luogo", "quadra", "campo", "estádio", "esporte", "lugar"], "translation": {"es": "cancha, campo (de juego)", "en": "court, field", "fr": "terrain de jeu", "de": "Spielfeld", "it": "campo da gioco", "pt": "quadra, campo"}},
    {"num": 19, "id": 11319, "traditional": "體育館", "simplified": "体育馆", "pinyin": "tǐyùguǎn", "zhuyin": "ㄊㄧˇ ㄩˋ ㄍㄨㄢˇ", "type": "N", "tags": ["gimnasio", "estadio", "arena", "deporte", "edificio", "gymnasium", "stadium", "arena", "sport", "building", "gymnase", "stade", "arène", "sport", "bâtiment", "Turnhalle", "Stadion", "Arena", "Sport", "Gebäude", "palestra", "stadio", "arena", "sport", "edificio", "ginásio", "estádio", "arena", "esporte", "prédio"], "translation": {"es": "gimnasio, estadio", "en": "gymnasium, stadium", "fr": "gymnase, stade", "de": "Turnhalle, Stadion", "it": "palestra, stadio", "pt": "ginásio, estádio"}},
    {"num": 20, "id": 11320, "traditional": "分數", "simplified": "分数", "pinyin": "fēnshù", "zhuyin": "ㄈㄣ ㄕㄨˋ", "type": "N", "tags": ["puntuación", "puntos", "resultado", "juego", "número", "score", "points", "result", "game", "number", "score", "points", "résultat", "jeu", "nombre", "Punktestand", "Punkte", "Ergebnis", "Spiel", "Zahl", "punteggio", "punti", "risultato", "gioco", "numero", "placar", "pontos", "resultado", "jogo", "número"], "translation": {"es": "puntuación", "en": "score", "fr": "score", "de": "Punktestand", "it": "punteggio", "pt": "placar"}},
    {"num": 21, "id": 11321, "traditional": "加油", "simplified": "加油", "pinyin": "jiāyóu", "zhuyin": "ㄐㄧㄚ ㄧㄡˊ", "type": "V-sep", "tags": ["animar", "vamos", "expresión", "apoyo", "motivación", "to cheer on", "go for it", "expression", "support", "motivation", "encourager", "allez", "expression", "soutien", "motivation", "anfeuern", "auf geht's", "Ausdruck", "Unterstützung", "Motivation", "fare il tifo", "forza", "espressione", "sostegno", "motivazione", "torcer", "vamos lá", "expressão", "apoio", "motivação"], "translation": {"es": "¡Vamos!", "en": "Go for it! / Cheer on", "fr": "Allez !", "de": "Auf geht's!", "it": "Forza!", "pt": "Vamos lá!"}},
    {"num": 22, "id": 11322, "traditional": "奧運", "simplified": "奥运", "pinyin": "Àoyùn", "zhuyin": "ㄠˋ ㄩㄣˋ", "type": "N", "tags": ["olimpiadas", "juegos olímpicos", "deporte", "internacional", "evento", "Olympics", "Olympic Games", "sport", "international", "event", "Jeux Olympiques", "sport", "international", "événement", "Olympiade", "Olympische Spiele", "Sport", "international", "Veranstaltung", "Olimpiadi", "Giochi Olimpici", "sport", "internazionale", "evento", "Olimpíadas", "Jogos Olímpicos", "esporte", "internacional", "evento"], "translation": {"es": "Juegos Olímpicos", "en": "Olympics", "fr": "Jeux Olympiques", "de": "Olympiade", "it": "Olimpiadi", "pt": "Olimpíadas"}},
    {"num": 23, "id": 11323, "traditional": "世界盃", "simplified": "世界杯", "pinyin": "Shìjièbēi", "zhuyin": "ㄕˋ ㄐㄧㄝˋ ㄅㄟ", "type": "N", "tags": ["copa del mundo", "fútbol", "competencia", "mundial", "evento", "World Cup", "soccer", "football", "competition", "global", "event", "Coupe du Monde", "football", "compétition", "mondial", "événement", "Weltmeisterschaft", "Fußball", "Wettbewerb", "weltweit", "Veranstaltung", "Coppa del Mondo", "calcio", "competizione", "mondiale", "evento", "Copa do Mundo", "futebol", "competição", "mundial", "evento"], "translation": {"es": "Copa del Mundo", "en": "World Cup", "fr": "Coupe du Monde", "de": "Weltmeisterschaft", "it": "Coppa del Mondo", "pt": "Copa do Mundo"}},
    {"num": 24, "id": 11324, "traditional": "健身房", "simplified": "健身房", "pinyin": "jiànshēnfáng", "zhuyin": "ㄐㄧㄢˋ ㄕㄣ ㄈㄤˊ", "type": "N", "tags": ["gimnasio", "fitness", "ejercicio", "salud", "lugar", "gym", "fitness", "exercise", "health", "place", "salle de sport", "fitness", "exercice", "santé", "lieu", "Fitnessstudio", "Fitness", "Übung", "Gesundheit", "Ort", "palestra", "fitness", "esercizio", "salute", "luogo", "academia", "fitness", "exercício", "saúde", "lugar"], "translation": {"es": "gimnasio", "en": "gym", "fr": "salle de sport", "de": "Fitnessstudio", "it": "palestra", "pt": "academia"}},
    {"num": 25, "id": 11325, "traditional": "羽毛球", "simplified": "羽毛球", "pinyin": "yǔmáoqiú", "zhuyin": "ㄩˇ ㄇㄠˊ ㄑㄧㄡˊ", "type": "N", "tags": ["deporte", "bádminton", "raqueta", "volante", "juego", "sport", "badminton", "racket", "shuttlecock", "game", "sport", "badminton", "raquette", "volant", "jeu", "Sport", "Badminton", "Federball", "Schläger", "Spiel", "sport", "badminton", "volano", "racchetta", "gioco", "esporte", "badminton", "peteca", "raquete", "jogo"], "translation": {"es": "bádminton", "en": "badminton", "fr": "badminton", "de": "Badminton", "it": "badminton", "pt": "badminton"}},
    {"num": 26, "id": 11326, "traditional": "排球", "simplified": "排球", "pinyin": "páiqiú", "zhuyin": "ㄆㄞˊ ㄑㄧㄡˊ", "type": "N", "tags": ["deporte", "voleibol", "juego de pelota", "equipo", "red", "sport", "volleyball", "ball game", "team", "net", "sport", "volley-ball", "jeu de balle", "équipe", "filet", "Sport", "Volleyball", "Ballspiel", "Mannschaft", "Netz", "sport", "pallavolo", "gioco con la palla", "squadra", "rete", "esporte", "vôlei", "jogo de bola", "equipe", "rede"], "translation": {"es": "voleibol", "en": "volleyball", "fr": "volley-ball", "de": "Volleyball", "it": "pallavolo", "pt": "vôlei"}},
    {"num": 27, "id": 11327, "traditional": "桌球", "simplified": "桌球", "pinyin": "zhuōqiú", "zhuyin": "ㄓㄨㄛ ㄑㄧㄡˊ", "type": "N", "tags": ["deporte", "tenis de mesa", "ping-pong", "raqueta", "juego", "sport", "table tennis", "ping-pong", "racket", "game", "sport", "tennis de table", "ping-pong", "raquette", "jeu", "Sport", "Tischtennis", "Ping-Pong", "Schläger", "Spiel", "sport", "ping-pong", "tennistavolo", "racchetta", "gioco", "esporte", "tênis de mesa", "pingue-pongue", "raquete", "jogo"], "translation": {"es": "tenis de mesa", "en": "table tennis", "fr": "tennis de table", "de": "Tischtennis", "it": "ping-pong", "pt": "tênis de mesa"}},
    {"num": 28, "id": 11328, "traditional": "高爾夫球", "simplified": "高尔夫球", "pinyin": "gāo'ěrfūqiú", "zhuyin": "ㄍㄠ ㄦˇ ㄈㄨ ㄑㄧㄡˊ", "type": "N", "tags": ["deporte", "golf", "palo", "hoyo", "campo", "sport", "golf", "club", "hole", "course", "sport", "golf", "club", "trou", "parcours", "Sport", "Golf", "Schläger", "Loch", "Platz", "sport", "golf", "mazza", "buca", "campo", "esporte", "golfe", "taco", "buraco", "campo"], "translation": {"es": "golf", "en": "golf", "fr": "golf", "de": "Golf", "it": "golf", "pt": "golfe"}},
    {"num": 29, "id": 11329, "traditional": "保齡球", "simplified": "保龄球", "pinyin": "bǎolíngqiú", "zhuyin": "ㄅㄠˇ ㄌㄧㄥˊ ㄑㄧㄡˊ", "type": "N", "tags": ["deporte", "bolos", "juego", "pista", "bola", "sport", "bowling", "game", "lane", "ball", "sport", "bowling", "jeu", "piste", "boule", "Sport", "Bowling", "Spiel", "Bahn", "Kugel", "sport", "bowling", "gioco", "pista", "palla", "esporte", "boliche", "jogo", "pista", "bola"], "translation": {"es": "bolos", "en": "bowling", "fr": "bowling", "de": "Bowling", "it": "bowling", "pt": "boliche"}},
    {"num": 30, "id": 11330, "traditional": "滑雪", "simplified": "滑雪", "pinyin": "huáxuě", "zhuyin": "ㄏㄨㄚˊ ㄒㄩㄝˇ", "type": "V", "tags": ["acción", "esquiar", "deporte de invierno", "nieve", "montaña", "action", "to ski", "winter sport", "snow", "mountain", "action", "skier", "sport d'hiver", "neige", "montagne", "Aktion", "Ski fahren", "Wintersport", "Schnee", "Berg", "azione", "sciare", "sport invernale", "neve", "montagna", "ação", "esquiar", "esporte de inverno", "neve", "montanha"], "translation": {"es": "esquiar", "en": "to ski", "fr": "skier", "de": "Ski fahren", "it": "sciare", "pt": "esquiar"}},
    {"num": 31, "id": 11331, "traditional": "溜冰", "simplified": "溜冰", "pinyin": "liūbīng", "zhuyin": "ㄌㄧㄡ ㄅㄧㄥ", "type": "V", "tags": ["acción", "patinar sobre hielo", "deporte de invierno", "hielo", "patines", "action", "to ice skate", "winter sport", "ice", "skates", "action", "patiner sur glace", "sport d'hiver", "glace", "patins", "Aktion", "Schlittschuh laufen", "Eislaufen", "Wintersport", "Eis", "Schlittschuhe", "azione", "pattinare su ghiaccio", "sport invernale", "ghiaccio", "pattini", "ação", "patinar no gelo", "esporte de inverno", "gelo", "patins"], "translation": {"es": "patinar sobre hielo", "en": "to ice skate", "fr": "patiner sur glace", "de": "Schlittschuh laufen", "it": "pattinare su ghiaccio", "pt": "patinar no gelo"}},
    {"num": 32, "id": 11332, "traditional": "裁判", "simplified": "裁判", "pinyin": "cáipàn", "zhuyin": "ㄘㄞˊ ㄆㄢˋ", "type": "N", "tags": ["árbitro", "juez", "deporte", "persona", "reglas", "referee", "umpire", "judge", "sport", "person", "rules", "arbitre", "juge", "sport", "personne", "règles", "Schiedsrichter", "Richter", "Sport", "Person", "Regeln", "arbitro", "giudice", "sport", "persona", "regole", "árbitro", "juiz", "esporte", "pessoa", "regras"], "translation": {"es": "árbitro", "en": "referee", "fr": "arbitre", "de": "Schiedsrichter", "it": "arbitro", "pt": "árbitro"}},
    {"num": 33, "id": 11333, "traditional": "球迷", "simplified": "球迷", "pinyin": "qiúmí", "zhuyin": "ㄑㄧㄡˊ ㄇㄧˊ", "type": "N", "tags": ["aficionado", "hincha", "fan", "deporte", "persona", "fan", "supporter", "sport", "person", "enthusiast", "fan", "supporter", "sport", "personne", "enthousiaste", "Fan", "Anhänger", "Sport", "Person", "Enthusiast", "tifoso", "sostenitore", "sport", "persona", "appassionato", "torcedor", "fã", "esporte", "pessoa", "entusiasta"], "translation": {"es": "aficionado a los deportes", "en": "sports fan", "fr": "fan de sport", "de": "Sportfan", "it": "tifoso sportivo", "pt": "fã de esportes"}},
    {"num": 34, "id": 11334, "traditional": "熱身", "simplified": "热身", "pinyin": "rèshēn", "zhuyin": "ㄖㄜˋ ㄕㄣ", "type": "V", "tags": ["acción", "calentar", "preparación", "ejercicio", "cuerpo", "action", "to warm up", "preparation", "exercise", "body", "action", "s'échauffer", "préparation", "exercice", "corps", "Aktion", "sich aufwärmen", "Vorbereitung", "Übung", "Körper", "azione", "riscaldarsi", "preparazione", "esercizio", "corpo", "ação", "aquecer", "preparação", "exercício", "corpo"], "translation": {"es": "calentar (ejercicio)", "en": "to warm up", "fr": "s'échauffer", "de": "sich aufwärmen", "it": "riscaldarsi", "pt": "aquecer"}},
    {"num": 35, "id": 11335, "traditional": "運動員", "simplified": "运动员", "pinyin": "yùndòngyuán", "zhuyin": "ㄩㄣˋ ㄉㄨㄥˋ ㄩㄢˊ", "type": "N", "tags": ["atleta", "deportista", "persona", "profesión", "competencia", "athlete", "sportsperson", "person", "profession", "competition", "athlète", "sportif", "personne", "profession", "compétition", "Athlet", "Sportler", "Person", "Beruf", "Wettbewerb", "atleta", "sportivo", "persona", "professione", "competizione", "atleta", "esportista", "pessoa", "profissão", "competição"], "translation": {"es": "atleta", "en": "athlete", "fr": "athlète", "de": "Athlet", "it": "atleta", "pt": "atleta"}},
    {"num": 36, "id": 11336, "traditional": "體操", "simplified": "体操", "pinyin": "tǐcāo", "zhuyin": "ㄊㄧˇ ㄘㄠ", "type": "N", "tags": ["deporte", "gimnasia", "acrobacia", "flexibilidad", "fuerza", "sport", "gymnastics", "acrobatics", "flexibility", "strength", "sport", "gymnastique", "acrobatie", "souplesse", "force", "Sport", "Turnen", "Gymnastik", "Akrobatik", "Flexibilität", "Kraft", "sport", "ginnastica", "acrobazia", "flessibilità", "forza", "esporte", "ginástica", "acrobacia", "flexibilidade", "força"], "translation": {"es": "gimnasia", "en": "gymnastics", "fr": "gymnastique", "de": "Turnen", "it": "ginnastica", "pt": "ginástica"}},
    {"num": 37, "id": 11337, "traditional": "馬拉松", "simplified": "马拉松", "pinyin": "mǎlāsōng", "zhuyin": "ㄇㄚˇ ㄌㄚ ㄙㄨㄥ", "type": "N", "tags": ["deporte", "maratón", "correr", "resistencia", "carrera", "sport", "marathon", "running", "endurance", "race", "sport", "marathon", "course à pied", "endurance", "course", "Sport", "Marathon", "Laufen", "Ausdauer", "Rennen", "sport", "maratona", "corsa", "resistenza", "gara", "esporte", "maratona", "corrida", "resistência", "corrida"], "translation": {"es": "maratón", "en": "marathon", "fr": "marathon", "de": "Marathon", "it": "maratona", "pt": "maratona"}},
    {"num": 38, "id": 11338, "traditional": "健行", "simplified": "健行", "pinyin": "jiànxíng", "zhuyin": "ㄐㄧㄢˋ ㄒㄧㄥˊ", "type": "V", "tags": ["acción", "senderismo", "caminar", "naturaleza", "montaña", "action", "hiking", "walking", "nature", "mountain", "action", "randonnée", "marche", "nature", "montagne", "Aktion", "wandern", "gehen", "Natur", "Berg", "azione", "escursionismo", "camminare", "natura", "montagna", "ação", "caminhada", "trilha", "natureza", "montanha"], "translation": {"es": "hacer senderismo", "en": "to hike", "fr": "faire de la randonnée", "de": "wandern", "it": "fare escursionismo", "pt": "fazer trilha"}},
    {"num": 39, "id": 11339, "traditional": "潛水", "simplified": "潜水", "pinyin": "qiánshuǐ", "zhuyin": "ㄑㄧㄢˊ ㄕㄨㄟˇ", "type": "V", "tags": ["acción", "bucear", "deporte acuático", "agua", "océano", "action", "to dive", "scuba diving", "water sport", "ocean", "action", "plonger", "plongée sous-marine", "sport aquatique", "océan", "Aktion", "tauchen", "Sporttauchen", "Wassersport", "Ozean", "azione", "immergersi", "subacquea", "sport acquatico", "oceano", "ação", "mergulhar", "esporte aquático", "água", "oceano"], "translation": {"es": "bucear", "en": "to dive, scuba diving", "fr": "plonger", "de": "tauchen", "it": "fare immersioni", "pt": "mergulhar"}},
    {"num": 40, "id": 11340, "traditional": "衝浪", "simplified": "冲浪", "pinyin": "chōnglàng", "zhuyin": "ㄔㄨㄥ ㄌㄤˋ", "type": "V", "tags": ["acción", "surfear", "deporte acuático", "olas", "mar", "action", "to surf", "water sport", "waves", "sea", "action", "surfer", "sport aquatique", "vagues", "mer", "Aktion", "surfen", "Wassersport", "Wellen", "Meer", "azione", "surfare", "sport acquatico", "onde", "mare", "ação", "surfar", "esporte aquático", "ondas", "mar"], "translation": {"es": "surfear", "en": "to surf", "fr": "surfer", "de": "surfen", "it": "fare surf", "pt": "surfar"}},
    {"num": 41, "id": 11341, "traditional": "溜滑板", "simplified": "溜滑板", "pinyin": "liū huábǎn", "zhuyin": "ㄌㄧㄡ ㄏㄨㄚˊ ㄅㄢˇ", "type": "V-sep", "tags": ["acción", "patinar (skateboard)", "deporte urbano", "tabla", "calle", "action", "to skateboard", "urban sport", "board", "street", "action", "faire du skateboard", "sport urbain", "planche", "rue", "Aktion", "Skateboard fahren", "Stadtsport", "Brett", "Straße", "azione", "andare in skateboard", "sport urbano", "tavola", "strada", "ação", "andar de skate", "esporte urbano", "prancha", "rua"], "translation": {"es": "andar en patineta", "en": "to skateboard", "fr": "faire du skateboard", "de": "Skateboard fahren", "it": "andare in skateboard", "pt": "andar de skate"}},
    {"num": 42, "id": 11342, "traditional": "龍舟", "simplified": "龙舟", "pinyin": "lóngzhōu", "zhuyin": "ㄌㄨㄥˊ ㄓㄡ", "type": "N", "tags": ["barco dragón", "deporte", "tradición", "festival", "carrera", "dragon boat", "sport", "tradition", "festival", "race", "bateau-dragon", "sport", "tradition", "festival", "course", "Drachenboot", "Sport", "Tradition", "Fest", "Rennen", "barca drago", "sport", "tradizione", "festival", "gara", "barco-dragão", "esporte", "tradição", "festival", "corrida"], "translation": {"es": "barco dragón", "en": "dragon boat", "fr": "bateau-dragon", "de": "Drachenboot", "it": "barca drago", "pt": "barco-dragão"}},
    {"num": 43, "id": 11343, "traditional": "獎牌", "simplified": "奖牌", "pinyin": "jiǎngpái", "zhuyin": "ㄐㄧㄤˇ ㄆㄞˊ", "type": "N", "tags": ["medalla", "premio", "competencia", "oro", "plata", "medal", "award", "prize", "competition", "gold", "silver", "médaille", "prix", "récompense", "compétition", "or", "argent", "Medaille", "Preis", "Auszeichnung", "Wettbewerb", "Gold", "Silber", "medaglia", "premio", "competizione", "oro", "argento", "medalha", "prêmio", "competição", "ouro", "prata"], "translation": {"es": "medalla", "en": "medal", "fr": "médaille", "de": "Medaille", "it": "medaglia", "pt": "medalha"}},
    {"num": 44, "id": 11344, "traditional": "奧林匹克", "simplified": "奥林匹克", "pinyin": "Àolínpǐkè", "zhuyin": "ㄠˋ ㄌㄧㄣˊ ㄆㄧˇ ㄎㄜˋ", "type": "N", "tags": ["olímpico", "deporte", "juegos", "internacional", "adjetivo", "Olympic", "sport", "games", "international", "adjective", "olympique", "sport", "jeux", "international", "adjectif", "olympisch", "Sport", "Spiele", "international", "Adjektiv", "olimpico", "sport", "giochi", "internazionale", "aggettivo", "olímpico", "esporte", "jogos", "internacional", "adjetivo"], "translation": {"es": "Olímpico", "en": "Olympic", "fr": "Olympique", "de": "olympisch", "it": "Olimpico", "pt": "Olímpico"}},
    {"num": 45, "id": 11345, "traditional": "規則", "simplified": "规则", "pinyin": "guīzé", "zhuyin": "ㄍㄨㄟ ㄗㄜˊ", "type": "N", "tags": ["reglas", "normas", "deporte", "juego", "ley", "rules", "regulations", "sport", "game", "law", "règles", "règlements", "sport", "jeu", "loi", "Regeln", "Vorschriften", "Sport", "Spiel", "Gesetz", "regole", "regolamenti", "sport", "gioco", "legge", "regras", "regulamentos", "esporte", "jogo", "lei"], "translation": {"es": "reglas", "en": "rules", "fr": "règles", "de": "Regeln", "it": "regole", "pt": "regras"}},
    {"num": 46, "id": 11346, "traditional": "團隊合作", "simplified": "团队合作", "pinyin": "tuánduì hézuò", "zhuyin": "ㄊㄨㄢˊ ㄉㄨㄟˋ ㄏㄜˊ ㄗㄨㄛˋ", "type": "N", "tags": ["trabajo en equipo", "cooperación", "equipo", "deporte", "colaboración", "teamwork", "cooperation", "team", "sport", "collaboration", "travail d'équipe", "coopération", "équipe", "sport", "collaboration", "Teamarbeit", "Zusammenarbeit", "Team", "Sport", "Kooperation", "lavoro di squadra", "cooperazione", "squadra", "sport", "collaborazione", "trabalho em equipe", "cooperação", "equipe", "esporte", "colaboração"], "translation": {"es": "trabajo en equipo", "en": "teamwork", "fr": "travail d'équipe", "de": "Teamarbeit", "it": "lavoro di squadra", "pt": "trabalho em equipe"}},
    {"num": 47, "id": 11347, "traditional": "犯規", "simplified": "犯规", "pinyin": "fànguī", "zhuyin": "ㄈㄢˋ ㄍㄨㄟ", "type": "V-sep", "tags": ["acción", "cometer una falta", "infracción", "reglas", "deporte", "action", "to commit a foul", "infraction", "rules", "sport", "action", "commettre une faute", "infraction", "règles", "sport", "Aktion", "ein Foul begehen", "Verstoß", "Regeln", "Sport", "azione", "commettere un fallo", "infrazione", "regole", "sport", "ação", "cometer uma falta", "infração", "regras", "esporte"], "translation": {"es": "cometer una falta", "en": "to commit a foul", "fr": "commettre une faute", "de": "ein Foul begehen", "it": "commettere un fallo", "pt": "cometer uma falta"}},
    {"num": 48, "id": 11348, "traditional": "進球", "simplified": "进球", "pinyin": "jìnqiú", "zhuyin": "ㄐㄧㄣˋ ㄑㄧㄡˊ", "type": "V-sep", "tags": ["acción", "marcar un gol", "anotar", "fútbol", "baloncesto", "action", "to score a goal", "soccer", "basketball", "point", "action", "marquer un but", "football", "basket-ball", "point", "Aktion", "ein Tor schießen", "punkten", "Fußball", "Basketball", "azione", "segnare un gol", "calcio", "pallacanestro", "punto", "ação", "marcar um gol", "futebol", "basquete", "ponto"], "translation": {"es": "marcar un gol", "en": "to score a goal", "fr": "marquer un but", "de": "ein Tor schießen", "it": "segnare un gol", "pt": "marcar um gol"}},
    {"num": 49, "id": 11349, "traditional": "守門員", "simplified": "守门员", "pinyin": "shǒuményuán", "zhuyin": "ㄕㄡˇ ㄇㄣˊ ㄩㄢˊ", "type": "N", "tags": ["portero", "guardameta", "fútbol", "equipo", "posición", "goalkeeper", "goalie", "soccer", "team", "position", "gardien de but", "football", "équipe", "position", "Torwart", "Fußball", "Mannschaft", "Position", "portiere", "calcio", "squadra", "posizione", "goleiro", "futebol", "equipe", "posição"], "translation": {"es": "portero", "en": "goalkeeper", "fr": "gardien de but", "de": "Torwart", "it": "portiere", "pt": "goleiro"}},
    {"num": 50, "id": 11350, "traditional": "啦啦隊", "simplified": "啦啦队", "pinyin": "lālāduì", "zhuyin": "ㄌㄚ ㄌㄚ ㄉㄨㄟˋ", "type": "N", "tags": ["animadoras", "equipo de animadores", "deporte", "apoyo", "baile", "cheerleader", "cheer squad", "sport", "support", "dance", "pom-pom girl", "équipe de cheerleading", "sport", "soutien", "danse", "Cheerleader", "Sport", "Unterstützung", "Tanz", "cheerleader", "squadra di cheerleader", "sport", "sostegno", "danza", "líder de torcida", "equipe de animação", "esporte", "apoio", "dança"], "translation": {"es": "equipo de animadoras", "en": "cheerleading squad", "fr": "équipe de cheerleaders", "de": "Cheerleader-Team", "it": "squadra di cheerleader", "pt": "equipe de líderes de torcida"}},
    {"num": 51, "id": 11351, "traditional": "體育", "simplified": "体育", "pinyin": "tǐyù", "zhuyin": "ㄊㄧˇ ㄩˋ", "type": "N", "tags": ["educación física", "deporte", "escuela", "actividad", "salud", "physical education", "P.E.", "sport", "school", "activity", "éducation physique", "EPS", "sport", "école", "activité", "Sportunterricht", "Turnen", "Schule", "Aktivität", "Gesundheit", "educazione fisica", "sport", "scuola", "attività", "salute", "educação física", "esporte", "escola", "atividade", "saúde"], "translation": {"es": "educación física", "en": "physical education", "fr": "éducation physique", "de": "Sportunterricht", "it": "educazione fisica", "pt": "educação física"}}
]
